{
   "!ALL":{
      "5.36.0":102941,
      "datetime":"2022-06-06T11:57:45",
      "perls":[
         "5.34.1",
         "5.36.0"
      ],
      "totalrcdists":20238
   },
   "!CAND":{
      "Acme-Brainfuck":{
         "1.1.1":{
            "5.34.1":{
               "pass":5
            },
            "5.36.0":{
               "fail":1
            }
         }
      },
      "Acme-CPANAuthors-French":{
         "0.09":{
            "5.34.1":{
               "fail":10,
               "pass":2
            },
            "5.36.0":{
               "fail":6
            }
         }
      },
      "Acme-LOLCAT":{
         "0.0.5":{
            "5.34.1":{
               "fail":4,
               "pass":2
            },
            "5.36.0":{
               "fail":1
            }
         }
      },
      "Acme-Tools":{
         "0.27":{
            "5.34.1":{
               "pass":6
            },
            "5.36.0":{
               "fail":1,
               "pass":5
            }
         }
      },
      "Algorithm-BloomFilter":{
         "0.02":{
            "5.34.1":{
               "pass":6
            },
            "5.36.0":{
               "fail":3,
               "pass":3
            }
         }
      },
      "Algorithm-QuadTree-XS":{
         "0.01":{
            "5.34.1":{
               "pass":20
            },
            "5.36.0":{
               "fail":1,
               "pass":20
            }
         }
      },
      "Alien-Judy":{
         "0.27":{
            "5.34.1":{
               "pass":5
            },
            "5.36.0":{
               "fail":3,
               "pass":3
            }
         }
      },
      "Alien-libtickit":{
         "0.12":{
            "5.34.1":{
               "pass":4
            },
            "5.36.0":{
               "fail":1,
               "pass":1
            }
         }
      },
      "Alien-nragent":{
         "0.08":{
            "5.34.1":{
               "fail":2,
               "pass":1
            },
            "5.36.0":{
               "fail":1
            }
         }
      },
      "AnyEvent-Gearman":{
         "0.10":{
            "5.34.1":{
               "pass":11
            },
            "5.36.0":{
               "fail":2,
               "pass":6
            }
         }
      },
      "Apache-BabyConnect":{
         "0.93":{
            "5.34.1":{
               "fail":3,
               "pass":1
            },
            "5.36.0":{
               "fail":1
            }
         }
      },
      "Apache-DBI-Cache":{
         "0.08":{
            "5.34.1":{
               "pass":2
            },
            "5.36.0":{
               "fail":2
            }
         }
      },
      "Apache-Session-Memorycached":{
         "2.2.1":{
            "5.34.1":{
               "fail":6,
               "pass":2
            },
            "5.36.0":{
               "fail":1
            }
         }
      },
      "App-CPAN-Dependents":{
         "1.000":{
            "5.34.1":{
               "pass":8
            },
            "5.36.0":{
               "fail":1,
               "pass":1
            }
         }
      },
      "App-DocKnot":{
         "7.01":{
            "5.34.1":{
               "pass":1
            },
            "5.36.0":{
               "fail":1
            }
         }
      },
      "App-Framework-Lite":{
         "1.09":{
            "5.34.1":{
               "pass":11
            },
            "5.36.0":{
               "fail":5
            }
         }
      },
      "App-Git-Workflow":{
         "v1.1.19":{
            "5.34.1":{
               "pass":13
            },
            "5.36.0":{
               "fail":1,
               "pass":14
            }
         }
      },
      "App-Stacktrace":{
         "0.09":{
            "5.34.1":{
               "fail":11,
               "pass":1
            },
            "5.36.0":{
               "fail":6
            }
         }
      },
      "App-Staticperl":{
         "1.46":{
            "5.34.1":{
               "fail":3,
               "pass":8
            },
            "5.36.0":{
               "fail":5
            }
         }
      },
      "App-pltest":{
         "v0.63.1":{
            "5.34.1":{
               "fail":11,
               "pass":6
            },
            "5.36.0":{
               "fail":5
            }
         }
      },
      "Archive-Libarchive-FFI":{
         "0.0902":{
            "5.34.1":{
               "pass":4
            },
            "5.36.0":{
               "fail":5
            }
         }
      },
      "Archive-Libarchive-XS":{
         "0.0903":{
            "5.34.1":{
               "fail":2,
               "pass":1
            },
            "5.36.0":{
               "fail":1
            }
         }
      },
      "Array-GroupBy":{
         "v0.0.4":{
            "5.34.1":{
               "pass":5
            },
            "5.36.0":{
               "fail":1
            }
         }
      },
      "Array-Splice":{
         "0.04":{
            "5.34.1":{
               "pass":6
            },
            "5.36.0":{
               "fail":1
            }
         }
      },
      "Astro-QDP-Parse":{
         "0.13":{
            "5.34.1":{
               "fail":6,
               "pass":2
            },
            "5.36.0":{
               "fail":1
            }
         }
      },
      "Astro-Units":{
         "1.10":{
            "5.34.1":{
               "fail":4,
               "pass":3
            },
            "5.36.0":{
               "fail":1
            }
         }
      },
      "Async-Microservice":{
         "0.02":{
            "5.34.1":{
               "fail":2,
               "pass":4
            },
            "5.36.0":{
               "fail":1
            }
         }
      },
      "Async-Trampoline":{
         "0.001002":{
            "5.34.1":{
               "fail":1,
               "pass":7
            },
            "5.36.0":{
               "fail":1
            }
         }
      },
      "Audio-File":{
         "0.11":{
            "5.34.1":{
               "fail":5,
               "pass":2
            },
            "5.36.0":{
               "fail":1
            }
         }
      },
      "Authen-Simple":{
         "0.5":{
            "5.34.1":{
               "pass":37
            },
            "5.36.0":{
               "fail":1,
               "pass":17
            }
         }
      },
      "Authen-Simple-NIS":{
         "0.3":{
            "5.34.1":{
               "pass":1
            },
            "5.36.0":{
               "fail":1
            }
         }
      },
      "B-DeparseTree":{
         "v3.4.0":{
            "5.34.1":{
               "pass":10
            },
            "5.36.0":{
               "fail":3
            }
         }
      },
      "Bio-GenBankParser":{
         "0.05":{
            "5.34.1":{
               "pass":2
            },
            "5.36.0":{
               "fail":1,
               "pass":1
            }
         }
      },
      "Business-OnlinePayment-SynapseGateway":{
         "0.01":{
            "5.34.1":{
               "pass":5
            },
            "5.36.0":{
               "fail":4
            }
         }
      },
      "CGI-Application-PhotoGallery":{
         "0.16":{
            "5.34.1":{
               "fail":6,
               "pass":1
            },
            "5.36.0":{
               "fail":1
            }
         }
      },
      "CGI-Application-Plugin-ProtectCSRF":{
         "1.01":{
            "5.34.1":{
               "fail":2,
               "pass":4
            },
            "5.36.0":{
               "fail":1
            }
         }
      },
      "CGI-FormBuilder":{
         "3.10":{
            "5.34.1":{
               "pass":22
            },
            "5.36.0":{
               "fail":1,
               "pass":9
            }
         }
      },
      "CGI-ProgressBar":{
         "0.05":{
            "5.34.1":{
               "pass":9
            },
            "5.36.0":{
               "fail":2
            }
         }
      },
      "CGI-Session-Driver-memcache":{
         "0.10":{
            "5.34.1":{
               "fail":2,
               "pass":4
            },
            "5.36.0":{
               "fail":1
            }
         }
      },
      "CGI-UploadEngine":{
         "0.93":{
            "5.34.1":{
               "fail":4,
               "pass":2
            },
            "5.36.0":{
               "fail":1
            }
         }
      },
      "CPAN-SQLite":{
         "0.219":{
            "5.34.1":{
               "fail":14,
               "pass":4
            },
            "5.36.0":{
               "fail":9
            }
         }
      },
      "CPAN-Test-Dummy-Perl5-UseUnsafeINC-Fail":{
         "0.04":{
            "5.34.1":{
               "fail":1,
               "pass":4
            },
            "5.36.0":{
               "fail":1
            }
         }
      },
      "Catalyst-Controller-SOAP":{
         "1.25":{
            "5.34.1":{
               "fail":9,
               "pass":2
            },
            "5.36.0":{
               "fail":6
            }
         }
      },
      "Catalyst-Model-FormFu":{
         "0.004":{
            "5.34.1":{
               "pass":1
            },
            "5.36.0":{
               "fail":1
            }
         }
      },
      "Catalyst-Plugin-C3":{
         "0.03":{
            "5.34.1":{
               "fail":6,
               "pass":1
            },
            "5.36.0":{
               "fail":3
            }
         }
      },
      "Catalyst-Plugin-CDBI-Transaction":{
         "0.03":{
            "5.34.1":{
               "fail":1,
               "pass":4
            },
            "5.36.0":{
               "fail":1
            }
         }
      },
      "Catalyst-Plugin-Charsets-Japanese":{
         "0.06":{
            "5.34.1":{
               "fail":2,
               "pass":3
            },
            "5.36.0":{
               "fail":1
            }
         }
      },
      "Catalyst-Plugin-Session-Store-TestMemcached":{
         "0.001":{
            "5.34.1":{
               "pass":2
            },
            "5.36.0":{
               "fail":1
            }
         }
      },
      "Catalyst-View-Mason":{
         "0.19":{
            "5.34.1":{
               "fail":9,
               "pass":2
            },
            "5.36.0":{
               "fail":7
            }
         }
      },
      "Cisco-ACL":{
         "0.12":{
            "5.34.1":{
               "fail":2,
               "pass":1
            },
            "5.36.0":{
               "fail":1
            }
         }
      },
      "Class-Builder":{
         "1.010":{
            "5.34.1":{
               "fail":6,
               "pass":1
            },
            "5.36.0":{
               "fail":1
            }
         }
      },
      "Class-DBI-View":{
         "0.07":{
            "5.34.1":{
               "fail":1,
               "pass":5
            },
            "5.36.0":{
               "fail":1
            }
         }
      },
      "Config-Context":{
         "0.10":{
            "5.34.1":{
               "pass":3
            },
            "5.36.0":{
               "fail":1
            }
         }
      },
      "Contenticious":{
         "0.393":{
            "5.34.1":{
               "fail":8,
               "pass":2
            },
            "5.36.0":{
               "fail":6
            }
         }
      },
      "Cpanel-JSON-XS":{
         "4.28":{
            "5.34.1":{
               "fail":1,
               "pass":39
            },
            "5.36.0":{
               "fail":1
            }
         }
      },
      "Crypt-MatrixSSL3":{
         "v3.9.3":{
            "5.34.1":{
               "fail":1,
               "pass":8
            },
            "5.36.0":{
               "fail":1
            }
         }
      },
      "Crypt-OpenSSL-Base-Func":{
         "0.035":{
            "5.34.1":{
               "fail":7,
               "pass":7
            },
            "5.36.0":{
               "fail":1
            }
         }
      },
      "Crypt-OpenSSL-CA":{
         "0.91":{
            "5.34.1":{
               "pass":5
            },
            "5.36.0":{
               "fail":2,
               "pass":2
            }
         }
      },
      "Crypt-SSLeay":{
         "0.72":{
            "5.34.1":{
               "fail":14,
               "pass":1
            },
            "5.36.0":{
               "fail":7
            }
         }
      },
      "Crypt-Skip32-Base32Crockford":{
         "0.33":{
            "5.34.1":{},
            "5.36.0":{
               "fail":1,
               "pass":1
            }
         }
      },
      "Curses-Simp":{
         "1.4.A8UG1gG":{
            "5.34.1":{
               "fail":1,
               "pass":1
            },
            "5.36.0":{
               "fail":1
            }
         }
      },
      "DBD-mysqlPPrawSjis":{
         "0.16":{
            "5.34.1":{
               "pass":7
            },
            "5.36.0":{
               "fail":1
            }
         }
      },
      "DBIx-ActiveRecord":{
         "0.03":{
            "5.34.1":{
               "pass":1
            },
            "5.36.0":{
               "fail":1
            }
         }
      },
      "DBIx-Class-PgLog":{
         "0.03":{
            "5.34.1":{
               "pass":1
            },
            "5.36.0":{
               "fail":1
            }
         }
      },
      "DBIx-Class-ResultSet-Void":{
         "0.07":{
            "5.34.1":{
               "pass":1
            },
            "5.36.0":{
               "fail":1,
               "pass":1
            }
         }
      },
      "Dancer-Plugin-SporeDefinitionControl":{
         "0.18":{
            "5.34.1":{
               "fail":8
            },
            "5.36.0":{
               "fail":4,
               "pass":1
            }
         }
      },
      "Data-Dump-XML":{
         "1.19":{
            "5.34.1":{
               "fail":12
            },
            "5.36.0":{
               "fail":5,
               "pass":1
            }
         }
      },
      "Data-Dumper-Interp":{
         "3.2":{
            "5.34.1":{
               "fail":8,
               "pass":4
            },
            "5.36.0":{
               "fail":1
            }
         }
      },
      "Data-Entropy":{
         "0.007":{
            "5.34.1":{
               "pass":49
            },
            "5.36.0":{
               "fail":8,
               "pass":45
            }
         }
      },
      "Data-ObjectDriver":{
         "0.21":{
            "5.34.1":{
               "pass":7
            },
            "5.36.0":{
               "fail":1,
               "pass":7
            }
         }
      },
      "Data-Pensieve":{
         "0.03a":{
            "5.34.1":{
               "fail":6,
               "pass":4
            },
            "5.36.0":{
               "fail":1
            }
         }
      },
      "Data-Sah-JS":{
         "0.87":{
            "5.34.1":{
               "fail":5,
               "pass":2
            },
            "5.36.0":{
               "fail":1
            }
         }
      },
      "Data-StreamDeserializer":{
         "0.06":{
            "5.34.1":{
               "pass":7
            },
            "5.36.0":{
               "fail":1,
               "pass":6
            }
         }
      },
      "Data-UUID-LibUUID":{
         "0.05":{
            "5.34.1":{
               "fail":12,
               "pass":1
            },
            "5.36.0":{
               "fail":6
            }
         }
      },
      "Date-JD":{
         "0.006":{
            "5.34.1":{
               "pass":6
            },
            "5.36.0":{
               "fail":5,
               "pass":6
            }
         }
      },
      "Date-Tiny":{
         "1.07":{
            "5.34.1":{
               "fail":11,
               "pass":5
            },
            "5.36.0":{
               "fail":5
            }
         }
      },
      "DateTime-Tiny":{
         "1.07":{
            "5.34.1":{
               "fail":12,
               "pass":6
            },
            "5.36.0":{
               "fail":5
            }
         }
      },
      "Debug-FaultAutoBT":{
         "0.02":{
            "5.34.1":{
               "pass":5
            },
            "5.36.0":{
               "fail":1
            }
         }
      },
      "Debug-LTrace":{
         "0.03":{
            "5.34.1":{
               "fail":2,
               "pass":1
            },
            "5.36.0":{
               "fail":1
            }
         }
      },
      "Desktop-Notify":{
         "0.05":{
            "5.34.1":{
               "fail":1,
               "pass":10
            },
            "5.36.0":{
               "fail":6
            }
         }
      },
      "Devel-DumpTrace":{
         "0.29":{
            "5.34.1":{
               "pass":7
            },
            "5.36.0":{
               "fail":1,
               "pass":4
            }
         }
      },
      "Devel-Memo":{
         "0.004":{
            "5.34.1":{
               "pass":1
            },
            "5.36.0":{
               "fail":1
            }
         }
      },
      "Devel-RingBuffer":{
         "0.31":{
            "5.34.1":{
               "fail":3,
               "pass":2
            },
            "5.36.0":{
               "fail":1
            }
         }
      },
      "Device-Firewall-PaloAlto":{
         "0.1.9":{
            "5.34.1":{
               "fail":5,
               "pass":3
            },
            "5.36.0":{
               "fail":1
            }
         }
      },
      "Device-OUI":{
         "1.04":{
            "5.34.1":{
               "fail":1,
               "pass":1
            },
            "5.36.0":{
               "fail":1
            }
         }
      },
      "Device-SerialPort":{
         "1.04":{
            "5.34.1":{
               "pass":11
            },
            "5.36.0":{
               "fail":1,
               "pass":7
            }
         }
      },
      "Dios":{
         "0.002012":{
            "5.34.1":{
               "pass":6
            },
            "5.36.0":{
               "fail":3
            }
         }
      },
      "Dist-Zilla":{
         "6.025":{
            "5.34.1":{
               "pass":39
            },
            "5.36.0":{
               "fail":1,
               "pass":53
            }
         }
      },
      "Dist-Zilla-Plugin-EnsurePrereqsInstalled":{
         "0.009":{
            "5.34.1":{
               "pass":2
            },
            "5.36.0":{
               "fail":1,
               "pass":2
            }
         }
      },
      "Dist-Zilla-Plugin-Prereqs-AuthorDeps":{
         "0.007":{
            "5.34.1":{
               "pass":18
            },
            "5.36.0":{
               "fail":1,
               "pass":9
            }
         }
      },
      "Dist-Zilla-Plugin-PromptIfStale":{
         "0.057":{
            "5.34.1":{
               "pass":10
            },
            "5.36.0":{
               "fail":1,
               "pass":10
            }
         }
      },
      "Dist-Zilla-Plugin-Run":{
         "0.048":{
            "5.34.1":{
               "pass":44
            },
            "5.36.0":{
               "fail":1,
               "pass":43
            }
         }
      },
      "Dist-Zilla-PluginBundle-ROKR":{
         "0.0019":{
            "5.34.1":{
               "fail":8,
               "pass":3
            },
            "5.36.0":{
               "fail":4
            }
         }
      },
      "EV-Hiredis":{
         "0.04":{
            "5.34.1":{
               "pass":5
            },
            "5.36.0":{
               "fail":1
            }
         }
      },
      "Elastic-Model":{
         "0.52":{
            "5.34.1":{
               "fail":5,
               "pass":1
            },
            "5.36.0":{
               "fail":1
            }
         }
      },
      "Feersum":{
         "1.410":{
            "5.34.1":{
               "pass":5
            },
            "5.36.0":{
               "fail":1,
               "pass":5
            }
         }
      },
      "File-CounterSS":{
         "0.01":{
            "5.34.1":{
               "fail":6,
               "pass":2
            },
            "5.36.0":{
               "fail":1
            }
         }
      },
      "Geo-Coder-List":{
         "0.29":{
            "5.34.1":{
               "fail":6,
               "pass":8
            },
            "5.36.0":{
               "fail":1
            }
         }
      },
      "Geo-GDAL":{
         "2.010301":{
            "5.34.1":{
               "pass":5
            },
            "5.36.0":{
               "fail":1,
               "pass":1
            }
         }
      },
      "Geo-GDAL-FFI":{
         "0.09":{
            "5.34.1":{
               "fail":2,
               "pass":1
            },
            "5.36.0":{
               "fail":1
            }
         }
      },
      "Git-MoreHooks":{
         "0.015":{
            "5.34.1":{
               "fail":19,
               "pass":4
            },
            "5.36.0":{
               "fail":25
            }
         }
      },
      "GitInsight":{
         "0.06":{
            "5.34.1":{
               "pass":1
            },
            "5.36.0":{
               "fail":1
            }
         }
      },
      "Gnuplot-Simple":{
         "0.013":{
            "5.34.1":{
               "pass":2
            },
            "5.36.0":{
               "fail":1
            }
         }
      },
      "Graphics-ColorObject":{
         "0.5.0":{
            "5.34.1":{
               "fail":6,
               "pass":2
            },
            "5.36.0":{
               "fail":3
            }
         }
      },
      "Graphics-Framebuffer":{
         "6.49":{
            "5.34.1":{
               "fail":1,
               "pass":4
            },
            "5.36.0":{
               "fail":1
            }
         }
      },
      "Graphics-GnuplotIF":{
         "1.8":{
            "5.34.1":{
               "pass":8
            },
            "5.36.0":{
               "fail":4,
               "pass":2
            }
         }
      },
      "Gtk2-Ex-Carp":{
         "0.01":{
            "5.34.1":{
               "fail":3,
               "pass":1
            },
            "5.36.0":{
               "fail":1
            }
         }
      },
      "HTML-TableExtract":{
         "2.15":{
            "5.34.1":{
               "pass":32
            },
            "5.36.0":{
               "fail":1,
               "pass":7
            }
         }
      },
      "Hash-SharedMem":{
         "0.005":{
            "5.34.1":{
               "pass":6
            },
            "5.36.0":{
               "fail":4,
               "pass":3
            }
         }
      },
      "Hiredis-Raw":{
         "0.07":{
            "5.34.1":{
               "fail":6,
               "pass":4
            },
            "5.36.0":{
               "fail":3
            }
         }
      },
      "Hypatia-GraphViz2":{
         "0.015":{
            "5.34.1":{
               "fail":5,
               "pass":2
            },
            "5.36.0":{
               "fail":1
            }
         }
      },
      "IPC-ConcurrencyLimit":{
         "0.17":{
            "5.34.1":{
               "pass":7
            },
            "5.36.0":{
               "fail":1,
               "pass":5
            }
         }
      },
      "IPC-Locker":{
         "1.500":{
            "5.34.1":{
               "pass":5
            },
            "5.36.0":{
               "fail":1,
               "pass":4
            }
         }
      },
      "IRC-Indexer":{
         "0.06":{
            "5.34.1":{
               "fail":3,
               "pass":4
            },
            "5.36.0":{
               "fail":1
            }
         }
      },
      "IS-Init":{
         "0.93":{
            "5.34.1":{
               "pass":1
            },
            "5.36.0":{
               "fail":1
            }
         }
      },
      "Image-Magick-Info":{
         "0.03":{
            "5.34.1":{
               "fail":4,
               "pass":2
            },
            "5.36.0":{
               "fail":1
            }
         }
      },
      "Image-Magick-Thumbnail-Simple":{
         "0.12":{
            "5.34.1":{
               "fail":7,
               "pass":2
            },
            "5.36.0":{
               "fail":1
            }
         }
      },
      "Image-Scale":{
         "0.14":{
            "5.34.1":{
               "pass":7
            },
            "5.36.0":{
               "fail":6
            }
         }
      },
      "Ingres-Utility-IINamu":{
         "0.07":{
            "5.34.1":{
               "fail":5,
               "pass":1
            },
            "5.36.0":{
               "fail":1
            }
         }
      },
      "Inline-Struct":{
         "0.30":{
            "5.34.1":{
               "pass":7
            },
            "5.36.0":{
               "fail":6
            }
         }
      },
      "JSYNC":{
         "0.25":{
            "5.34.1":{
               "fail":12,
               "pass":16
            },
            "5.36.0":{
               "fail":6
            }
         }
      },
      "Jabber-PubSub-JEAI":{
         "0.03":{
            "5.34.1":{
               "fail":7,
               "pass":3
            },
            "5.36.0":{
               "fail":1
            }
         }
      },
      "JavaScript-DebugConsole":{
         "0.01":{
            "5.34.1":{
               "pass":7
            },
            "5.36.0":{
               "fail":1
            }
         }
      },
      "Kwiki-DB":{
         "0.02":{
            "5.34.1":{
               "fail":2,
               "pass":5
            },
            "5.36.0":{
               "fail":1
            }
         }
      },
      "Kwiki-Prototype":{
         "0.01":{
            "5.34.1":{
               "pass":2
            },
            "5.36.0":{
               "fail":1
            }
         }
      },
      "Lexical-Importer":{
         "0.000005":{
            "5.34.1":{
               "pass":5
            },
            "5.36.0":{
               "fail":3,
               "pass":2
            }
         }
      },
      "Lingua-HU-Numbers":{
         "0.07":{
            "5.34.1":{
               "fail":10,
               "pass":1
            },
            "5.36.0":{
               "fail":5
            }
         }
      },
      "Lingua-ZH-Numbers":{
         "0.04":{
            "5.34.1":{
               "fail":6,
               "pass":2
            },
            "5.36.0":{
               "fail":6
            }
         }
      },
      "Lingua-ZH-PinyinConvert":{
         "0.05":{
            "5.34.1":{
               "fail":1,
               "pass":1
            },
            "5.36.0":{
               "fail":1
            }
         }
      },
      "Linux-GetPidstat":{
         "0.10":{
            "5.34.1":{
               "fail":8,
               "pass":3
            },
            "5.36.0":{
               "fail":1
            }
         }
      },
      "Linux-Socket-Accept4":{
         "0.05":{
            "5.34.1":{
               "pass":2
            },
            "5.36.0":{
               "fail":1
            }
         }
      },
      "List-MergeSorted-XS":{
         "1.06":{
            "5.34.1":{
               "pass":9
            },
            "5.36.0":{
               "fail":1,
               "pass":1
            }
         }
      },
      "Log-Dispatch-Growl":{
         "1.0.0":{
            "5.34.1":{
               "fail":2,
               "pass":4
            },
            "5.36.0":{
               "fail":1
            }
         }
      },
      "Lorem":{
         "0.22":{
            "5.34.1":{
               "fail":5,
               "pass":1
            },
            "5.36.0":{
               "fail":1
            }
         }
      },
      "Mail-GnuPG":{
         "0.23":{
            "5.34.1":{
               "fail":5,
               "pass":1
            },
            "5.36.0":{
               "fail":1
            }
         }
      },
      "Mail-SPF":{
         "v2.9.0":{
            "5.34.1":{
               "fail":3,
               "pass":1
            },
            "5.36.0":{
               "fail":1
            }
         }
      },
      "Mail-Sendmail":{
         "0.80":{
            "5.34.1":{
               "fail":8,
               "pass":2
            },
            "5.36.0":{
               "fail":7
            }
         }
      },
      "Mail-SimpleList":{
         "0.95":{
            "5.34.1":{
               "fail":4,
               "pass":2
            },
            "5.36.0":{
               "fail":1
            }
         }
      },
      "Marky":{
         "0.035":{
            "5.34.1":{
               "pass":1
            },
            "5.36.0":{
               "fail":1
            }
         }
      },
      "Math-BigInt-Lite":{
         "0.24":{
            "5.34.1":{
               "fail":1,
               "pass":6
            },
            "5.36.0":{
               "fail":2
            }
         }
      },
      "Math-Calc-Parser":{
         "1.005":{
            "5.34.1":{
               "fail":5,
               "pass":6
            },
            "5.36.0":{
               "fail":2
            }
         }
      },
      "Math-GSL-Linalg-SVD":{
         "0.0.2":{
            "5.34.1":{
               "pass":2
            },
            "5.36.0":{
               "fail":1
            }
         }
      },
      "Math-MatrixReal":{
         "2.13":{
            "5.34.1":{
               "pass":10
            },
            "5.36.0":{
               "fail":1,
               "pass":9
            }
         }
      },
      "Math-NumSeq":{
         "74":{
            "5.34.1":{
               "pass":6
            },
            "5.36.0":{
               "fail":4
            }
         }
      },
      "Math-Polynomial":{
         "1.021":{
            "5.34.1":{
               "pass":18
            },
            "5.36.0":{
               "fail":1,
               "pass":15
            }
         }
      },
      "Math-Polynomial-Multivariate":{
         "0.007":{
            "5.34.1":{
               "pass":1
            },
            "5.36.0":{
               "fail":1,
               "pass":1
            }
         }
      },
      "Math-Prime-TiedArray":{
         "0.04":{
            "5.34.1":{
               "fail":6,
               "pass":1
            },
            "5.36.0":{
               "fail":1
            }
         }
      },
      "Math-Random-Brownian":{
         "0.03":{
            "5.34.1":{
               "pass":1
            },
            "5.36.0":{
               "fail":1
            }
         }
      },
      "Math-Random-Normal-Leva":{
         "0.04":{
            "5.34.1":{
               "pass":7
            },
            "5.36.0":{
               "fail":1,
               "pass":5
            }
         }
      },
      "Math-Random-SkewNormal":{
         "0.03":{
            "5.34.1":{
               "fail":7,
               "pass":1
            },
            "5.36.0":{
               "fail":1
            }
         }
      },
      "Math-WalshTransform":{
         "1.17":{
            "5.34.1":{
               "pass":6
            },
            "5.36.0":{
               "fail":1
            }
         }
      },
      "Module-Build-XSUtil":{
         "0.19":{
            "5.34.1":{
               "pass":80
            },
            "5.36.0":{
               "fail":1,
               "pass":56
            }
         }
      },
      "Module-Dependency":{
         "1.86":{
            "5.34.1":{
               "fail":2,
               "pass":6
            },
            "5.36.0":{
               "fail":1
            }
         }
      },
      "Mojo-SMTP-Client":{
         "0.19":{
            "5.34.1":{
               "fail":2,
               "pass":4
            },
            "5.36.0":{
               "fail":1
            }
         }
      },
      "Mojo-UserAgent-Mockable":{
         "1.59":{
            "5.34.1":{
               "fail":8,
               "pass":7
            },
            "5.36.0":{
               "fail":3
            }
         }
      },
      "MojoX-JSON-RPC-Service-AutoRegister":{
         "0.001":{
            "5.34.1":{
               "fail":6,
               "pass":1
            },
            "5.36.0":{
               "fail":1
            }
         }
      },
      "Mojolicious-Plugin-Authentication":{
         "1.37":{
            "5.34.1":{
               "fail":6,
               "pass":9
            },
            "5.36.0":{
               "fail":8
            }
         }
      },
      "Mojolicious-Plugin-Authorization":{
         "1.06":{
            "5.34.1":{
               "fail":6,
               "pass":2
            },
            "5.36.0":{
               "fail":1
            }
         }
      },
      "Mojolicious-Plugin-DeCSRF":{
         "0.94":{
            "5.34.1":{
               "pass":1
            },
            "5.36.0":{
               "fail":1
            }
         }
      },
      "Mojolicious-Plugin-Prove":{
         "0.11":{
            "5.34.1":{
               "fail":2,
               "pass":5
            },
            "5.36.0":{
               "fail":1
            }
         }
      },
      "Mojolicious-Plugin-RedisSubscriber":{
         "0.0.1":{
            "5.34.1":{
               "fail":6,
               "pass":1
            },
            "5.36.0":{
               "fail":1
            }
         }
      },
      "MooX-Params-CompiledValidators":{
         "0.04_01":{
            "5.34.1":{
               "fail":24,
               "pass":1
            },
            "5.36.0":{
               "fail":28
            }
         },
         "0.04_02":{
            "5.34.1":{
               "fail":23,
               "pass":1
            },
            "5.36.0":{
               "fail":19
            }
         },
         "0.04_03":{
            "5.34.1":{
               "fail":34,
               "pass":1
            },
            "5.36.0":{
               "fail":31
            }
         }
      },
      "Net-Analysis":{
         "0.41":{
            "5.34.1":{
               "fail":3,
               "pass":1
            },
            "5.36.0":{
               "fail":1
            }
         }
      },
      "Net-Evernote-Simple":{
         "0.07":{
            "5.34.1":{
               "pass":1
            },
            "5.36.0":{
               "fail":1
            }
         }
      },
      "Net-FTP-Simple":{
         "0.0007":{
            "5.34.1":{
               "fail":1,
               "pass":5
            },
            "5.36.0":{
               "fail":1
            }
         }
      },
      "Net-HTTPS-Any":{
         "0.12":{
            "5.34.1":{
               "fail":1,
               "pass":13
            },
            "5.36.0":{
               "fail":7
            }
         }
      },
      "Net-IMAP-Server":{
         "1.39":{
            "5.34.1":{
               "pass":6
            },
            "5.36.0":{
               "fail":1,
               "pass":4
            }
         }
      },
      "Net-IPA":{
         "1.0":{
            "5.34.1":{
               "fail":5,
               "pass":2
            },
            "5.36.0":{
               "fail":1
            }
         }
      },
      "Net-Jabber":{
         "2.0":{
            "5.34.1":{
               "fail":6,
               "pass":5
            },
            "5.36.0":{
               "fail":1
            }
         }
      },
      "Net-LDAP-SimpleServer":{
         "0.0.21":{
            "5.34.1":{
               "pass":6
            },
            "5.36.0":{
               "fail":3,
               "pass":2
            }
         }
      },
      "Net-LibResolv":{
         "0.03":{
            "5.34.1":{
               "fail":2,
               "pass":2
            },
            "5.36.0":{
               "fail":1
            }
         }
      },
      "Net-NIS-Listgroup":{
         "1.0.0":{
            "5.34.1":{
               "pass":7
            },
            "5.36.0":{
               "fail":1
            }
         }
      },
      "Net-Semantics3":{
         "0.20":{
            "5.34.1":{
               "pass":2
            },
            "5.36.0":{
               "fail":1
            }
         }
      },
      "Net-ext":{
         "1.011":{
            "5.34.1":{
               "pass":6
            },
            "5.36.0":{
               "fail":1
            }
         }
      },
      "NewRelic-Agent":{
         "0.0532":{
            "5.34.1":{
               "fail":3,
               "pass":2
            },
            "5.36.0":{
               "fail":1
            }
         }
      },
      "News-GnusFilter":{
         "0.55":{
            "5.34.1":{
               "fail":3,
               "pass":2
            },
            "5.36.0":{
               "fail":1
            }
         }
      },
      "Number-Tolerant":{
         "1.709":{
            "5.34.1":{
               "pass":46
            },
            "5.36.0":{
               "fail":8,
               "pass":47
            }
         }
      },
      "Object-Pad":{
         "0.65":{
            "5.34.1":{
               "pass":35
            },
            "5.36.0":{
               "fail":2,
               "pass":31
            }
         }
      },
      "Object-WithParams":{
         "0.3":{
            "5.34.1":{
               "fail":10,
               "pass":1
            },
            "5.36.0":{
               "fail":5
            }
         }
      },
      "PMLTQ-Commands":{
         "2.0.3":{
            "5.34.1":{
               "fail":2,
               "pass":2
            },
            "5.36.0":{
               "fail":1
            }
         }
      },
      "POE-Component-Generic":{
         "0.1403":{
            "5.34.1":{
               "fail":3,
               "pass":7
            },
            "5.36.0":{
               "fail":6
            }
         }
      },
      "POE-Component-SSLify":{
         "1.012":{
            "5.34.1":{
               "fail":36,
               "pass":1
            },
            "5.36.0":{
               "fail":31
            }
         }
      },
      "POE-Component-Server-HTTP":{
         "0.09":{
            "5.34.1":{
               "pass":3
            },
            "5.36.0":{
               "fail":1,
               "pass":3
            }
         }
      },
      "POE-Loop-AnyEvent":{
         "0.004":{
            "5.34.1":{
               "pass":7
            },
            "5.36.0":{
               "fail":1,
               "pass":5
            }
         }
      },
      "POE-Loop-EV":{
         "0.14":{
            "5.34.1":{
               "pass":3
            },
            "5.36.0":{
               "fail":1,
               "pass":1
            }
         }
      },
      "POE-Loop-Tk":{
         "1.305":{
            "5.34.1":{
               "pass":7
            },
            "5.36.0":{
               "fail":1,
               "pass":6
            }
         }
      },
      "Parallel-Prefork":{
         "0.18":{
            "5.34.1":{
               "pass":12
            },
            "5.36.0":{
               "fail":1,
               "pass":7
            }
         }
      },
      "Parallel-Queue":{
         "v4.0.5":{
            "5.34.1":{
               "pass":6
            },
            "5.36.0":{
               "fail":2,
               "pass":3
            }
         }
      },
      "Parse-Debian-PackageDesc":{
         "0.15":{
            "5.34.1":{
               "fail":8,
               "pass":2
            },
            "5.36.0":{
               "fail":6
            }
         }
      },
      "Perinci-CmdLine-Inline":{
         "0.554":{
            "5.34.1":{
               "fail":10,
               "pass":1
            },
            "5.36.0":{
               "fail":6
            }
         }
      },
      "Perl-Critic":{
         "1.140":{
            "5.34.1":{
               "pass":63
            },
            "5.36.0":{
               "fail":1,
               "pass":59
            }
         }
      },
      "PerlBean":{
         "1.0":{
            "5.34.1":{
               "pass":6
            },
            "5.36.0":{
               "fail":1
            }
         }
      },
      "Pg-Reindex":{
         "0.001":{
            "5.34.1":{
               "pass":1
            },
            "5.36.0":{
               "fail":1
            }
         }
      },
      "PkgConfig-LibPkgConf":{
         "0.11":{
            "5.34.1":{
               "fail":1,
               "pass":9
            },
            "5.36.0":{
               "fail":1
            }
         }
      },
      "Pod-Query":{
         "0.08":{
            "5.34.1":{
               "fail":17,
               "pass":6
            },
            "5.36.0":{
               "fail":26
            }
         },
         "0.09":{
            "5.34.1":{
               "fail":27,
               "pass":7
            },
            "5.36.0":{
               "fail":31
            }
         }
      },
      "Pod-Weaver-Plugin-Ditaa":{
         "0.001006":{
            "5.34.1":{
               "fail":6,
               "pass":1
            },
            "5.36.0":{
               "fail":3
            }
         }
      },
      "Prima":{
         "1.65":{
            "5.34.1":{
               "pass":14
            },
            "5.36.0":{
               "fail":7,
               "pass":2
            }
         }
      },
      "Promise-ES6":{
         "0.25":{
            "5.34.1":{
               "pass":20
            },
            "5.36.0":{
               "fail":2,
               "pass":7
            }
         }
      },
      "RDF-Notation3":{
         "0.91":{
            "5.34.1":{
               "fail":2,
               "pass":6
            },
            "5.36.0":{
               "fail":6
            }
         }
      },
      "RDF-Trine-Node-Literal-XML":{
         "0.16":{
            "5.34.1":{
               "pass":6
            },
            "5.36.0":{
               "fail":2,
               "pass":3
            }
         }
      },
      "Reconcile-Accounts-Vin":{
         "1.03":{
            "5.34.1":{
               "fail":1,
               "pass":1
            },
            "5.36.0":{
               "fail":1
            }
         }
      },
      "Redis-CappedCollection":{
         "1.10":{
            "5.34.1":{
               "fail":1,
               "pass":6
            },
            "5.36.0":{
               "fail":2
            }
         }
      },
      "Redis-Fast":{
         "0.33":{
            "5.34.1":{
               "fail":7,
               "pass":4
            },
            "5.36.0":{
               "fail":7
            }
         }
      },
      "Regexp-Grammars":{
         "1.057":{
            "5.34.1":{
               "pass":66
            },
            "5.36.0":{
               "fail":1,
               "pass":52
            }
         }
      },
      "Rose-DBx-Object-Builder":{
         "0.09":{
            "5.34.1":{
               "fail":11,
               "pass":1
            },
            "5.36.0":{
               "fail":5
            }
         }
      },
      "SMS-Send-US-TMobile":{
         "v0.0.3":{
            "5.34.1":{
               "fail":6,
               "pass":17
            },
            "5.36.0":{
               "fail":1
            }
         }
      },
      "SNMP-Persist":{
         "0.05":{
            "5.34.1":{
               "fail":5,
               "pass":2
            },
            "5.36.0":{
               "fail":1
            }
         }
      },
      "SWISH-3":{
         "1.000015":{
            "5.34.1":{
               "pass":13
            },
            "5.36.0":{
               "fail":3,
               "pass":3
            }
         }
      },
      "Sailthru-Client":{
         "2.3.0":{
            "5.34.1":{
               "fail":4,
               "pass":2
            },
            "5.36.0":{
               "fail":1
            }
         }
      },
      "Scope-Escape":{
         "0.005":{
            "5.34.1":{
               "pass":10
            },
            "5.36.0":{
               "fail":6
            }
         }
      },
      "Script-Ichigeki":{
         "0.04":{
            "5.34.1":{
               "pass":2
            },
            "5.36.0":{
               "fail":1
            }
         }
      },
      "Serge":{
         "1.4":{
            "5.34.1":{
               "fail":2,
               "pass":4
            },
            "5.36.0":{
               "fail":1
            }
         }
      },
      "Seshat-Parallel":{
         "1.01":{
            "5.34.1":{
               "fail":6,
               "pass":5
            },
            "5.36.0":{
               "fail":1
            }
         }
      },
      "ShellScript-Env":{
         "0.4":{
            "5.34.1":{
               "fail":3,
               "pass":1
            },
            "5.36.0":{
               "fail":1
            }
         }
      },
      "Statistics-RatioVariance":{
         "1.00":{
            "5.34.1":{
               "fail":4,
               "pass":4
            },
            "5.36.0":{
               "fail":1
            }
         }
      },
      "Storable-AMF":{
         "1.23":{
            "5.34.1":{
               "pass":10
            },
            "5.36.0":{
               "fail":6
            }
         }
      },
      "Switch":{
         "2.17":{
            "5.34.1":{
               "pass":21
            },
            "5.36.0":{
               "fail":1,
               "pass":13
            }
         }
      },
      "Syntax-Keyword-Match":{
         "0.09":{
            "5.34.1":{
               "pass":34
            },
            "5.36.0":{
               "fail":1,
               "pass":12
            }
         }
      },
      "Sys-HostAddr":{
         "0.993":{
            "5.34.1":{
               "fail":2,
               "pass":10
            },
            "5.36.0":{
               "fail":6
            }
         }
      },
      "Sys-Lastlog":{
         "1.6":{
            "5.34.1":{
               "pass":2
            },
            "5.36.0":{
               "fail":1
            }
         }
      },
      "Sys-Prctl":{
         "1.02":{
            "5.34.1":{
               "fail":9,
               "pass":2
            },
            "5.36.0":{
               "fail":5
            }
         }
      },
      "TAP-Formatter-BambooExtended":{
         "1.01":{
            "5.34.1":{
               "fail":1,
               "pass":3
            },
            "5.36.0":{
               "fail":1
            }
         }
      },
      "Tempest":{
         "2010.09.26":{
            "5.34.1":{
               "fail":6
            },
            "5.36.0":{
               "fail":3,
               "pass":3
            }
         }
      },
      "Template-Plugin-HTML-SuperForm":{
         "1.0":{
            "5.34.1":{
               "pass":1
            },
            "5.36.0":{
               "fail":1
            }
         }
      },
      "Template-Plugin-SafeInclude":{
         "0.02":{
            "5.34.1":{
               "fail":3,
               "pass":4
            },
            "5.36.0":{
               "fail":1
            }
         }
      },
      "Term-Clear":{
         "0.01":{
            "5.34.1":{
               "fail":7,
               "pass":5
            },
            "5.36.0":{
               "fail":6
            }
         }
      },
      "Term-Table2":{
         "1.0.3":{
            "5.34.1":{
               "pass":6
            },
            "5.36.0":{
               "fail":1
            }
         }
      },
      "Test-Attribute-AutoLevel":{
         "0.06":{
            "5.34.1":{
               "pass":9
            },
            "5.36.0":{
               "fail":1
            }
         }
      },
      "Test-OnlySome":{
         "0.001005":{
            "5.34.1":{
               "fail":1,
               "pass":8
            },
            "5.36.0":{
               "fail":1
            }
         }
      },
      "Test-WWW-Simple":{
         "0.40":{
            "5.34.1":{
               "fail":4,
               "pass":1
            },
            "5.36.0":{
               "fail":1
            }
         }
      },
      "Test-XML-Simple":{
         "1.05":{
            "5.34.1":{
               "fail":3,
               "pass":2
            },
            "5.36.0":{
               "fail":1
            }
         }
      },
      "TestML1":{
         "0.57":{
            "5.34.1":{
               "fail":6,
               "pass":12
            },
            "5.36.0":{
               "fail":1
            }
         }
      },
      "Text-Decorator":{
         "1.65":{
            "5.34.1":{
               "fail":4,
               "pass":3
            },
            "5.36.0":{
               "fail":1
            }
         }
      },
      "Text-Match-FastAlternatives":{
         "1.05":{
            "5.34.1":{
               "fail":3,
               "pass":11
            },
            "5.36.0":{
               "fail":1
            }
         }
      },
      "Text-MiniTmpl":{
         "v2.0.1":{
            "5.34.1":{
               "pass":7
            },
            "5.36.0":{
               "fail":3,
               "pass":5
            }
         }
      },
      "Text-Summarize":{
         "0.50":{
            "5.34.1":{
               "fail":4,
               "pass":4
            },
            "5.36.0":{
               "fail":1
            }
         }
      },
      "Text-UnicodeBox":{
         "0.03":{
            "5.34.1":{
               "pass":10
            },
            "5.36.0":{
               "fail":1,
               "pass":10
            }
         }
      },
      "Text-Widont":{
         "0.01":{
            "5.34.1":{
               "fail":4,
               "pass":1
            },
            "5.36.0":{
               "fail":1
            }
         }
      },
      "Thread-Queue-Duplex":{
         "0.92":{
            "5.34.1":{
               "fail":3,
               "pass":2
            },
            "5.36.0":{
               "fail":1
            }
         }
      },
      "Thread-Serialize":{
         "1.02":{
            "5.34.1":{
               "pass":3
            },
            "5.36.0":{
               "fail":1
            }
         }
      },
      "Thread-Workers":{
         "0.06":{
            "5.34.1":{
               "fail":5,
               "pass":2
            },
            "5.36.0":{
               "fail":1
            }
         }
      },
      "Thrift-Parser":{
         "0.06":{
            "5.34.1":{
               "pass":2
            },
            "5.36.0":{
               "fail":1
            }
         }
      },
      "Tickit-Widget-Entry-Plugin-History":{
         "0.01":{
            "5.34.1":{
               "pass":2
            },
            "5.36.0":{
               "fail":1
            }
         }
      },
      "Tie-Array-Packed-Auto":{
         "0.03":{
            "5.34.1":{
               "pass":1
            },
            "5.36.0":{
               "fail":1
            }
         }
      },
      "Time-TCG":{
         "0.002":{
            "5.34.1":{
               "pass":6
            },
            "5.36.0":{
               "fail":1,
               "pass":2
            }
         }
      },
      "Time-Warp":{
         "0.54":{
            "5.34.1":{
               "fail":11,
               "pass":2
            },
            "5.36.0":{
               "fail":8
            }
         }
      },
      "Tk-DirSelect":{
         "1.12":{
            "5.34.1":{
               "fail":10,
               "pass":4
            },
            "5.36.0":{
               "fail":6
            }
         }
      },
      "Tree-Binary-XS":{
         "0.03":{
            "5.34.1":{
               "pass":1
            },
            "5.36.0":{
               "fail":1
            }
         }
      },
      "Tree-RB-XS":{
         "0.06":{
            "5.34.1":{
               "pass":14
            },
            "5.36.0":{
               "fail":9,
               "pass":7
            }
         }
      },
      "UI-Various":{
         "0.23":{
            "5.34.1":{
               "pass":42
            },
            "5.36.0":{
               "fail":1,
               "pass":42
            }
         }
      },
      "UnRTF":{
         "0.003":{
            "5.34.1":{
               "fail":1,
               "pass":6
            },
            "5.36.0":{
               "fail":1
            }
         }
      },
      "Unicode-BiDiRule":{
         "0.04":{
            "5.34.1":{
               "fail":6,
               "pass":2
            },
            "5.36.0":{
               "fail":1
            }
         }
      },
      "Unix-Lsof":{
         "0.1.0":{
            "5.34.1":{
               "fail":7,
               "pass":4
            },
            "5.36.0":{
               "fail":7
            }
         }
      },
      "Var-Mystic":{
         "0.000003":{
            "5.34.1":{
               "fail":2,
               "pass":1
            },
            "5.36.0":{
               "fail":1
            }
         }
      },
      "WWW-Form-UrlEncoded-XS":{
         "0.27":{
            "5.34.1":{
               "pass":16
            },
            "5.36.0":{
               "fail":2,
               "pass":1
            }
         }
      },
      "WWW-Google-Time":{
         "1.001005":{
            "5.34.1":{
               "fail":7,
               "pass":3
            },
            "5.36.0":{
               "fail":6
            }
         }
      },
      "WWW-Proxy4FreeCom":{
         "1.004002":{
            "5.34.1":{
               "fail":7,
               "pass":2
            },
            "5.36.0":{
               "fail":1
            }
         }
      },
      "WWW-Search-Ebay":{
         "3.056":{
            "5.34.1":{
               "fail":5,
               "pass":1
            },
            "5.36.0":{
               "fail":2
            }
         }
      },
      "WWW-Sitemapper":{
         "1.121160":{
            "5.34.1":{
               "pass":4
            },
            "5.36.0":{
               "fail":2,
               "pass":1
            }
         }
      },
      "Waft-JSON":{
         "0.03":{
            "5.34.1":{
               "fail":6,
               "pass":4
            },
            "5.36.0":{
               "fail":1
            }
         }
      },
      "WebService-Google-Contact":{
         "0.1":{
            "5.34.1":{
               "fail":2,
               "pass":3
            },
            "5.36.0":{
               "fail":1
            }
         }
      },
      "WebService-Google-Language":{
         "0.14":{
            "5.34.1":{
               "fail":6,
               "pass":4
            },
            "5.36.0":{
               "fail":5
            }
         }
      },
      "WebService-JugemKey-Auth":{
         "0.04":{
            "5.34.1":{
               "fail":1,
               "pass":1
            },
            "5.36.0":{
               "fail":1
            }
         }
      },
      "WebService-Uptrack":{
         "v0.0.2":{
            "5.34.1":{
               "fail":2,
               "pass":4
            },
            "5.36.0":{
               "fail":1
            }
         }
      },
      "Workflow-Wfmc":{
         "0.01e":{
            "5.34.1":{
               "fail":6,
               "pass":2
            },
            "5.36.0":{
               "fail":1
            }
         }
      },
      "XML-APML":{
         "0.04":{
            "5.34.1":{
               "fail":1,
               "pass":5
            },
            "5.36.0":{
               "fail":1
            }
         }
      },
      "XML-Feed":{
         "0.63":{
            "5.34.1":{
               "pass":39
            },
            "5.36.0":{
               "fail":1,
               "pass":7
            }
         }
      },
      "XML-Filter-Conditional":{
         "0.05":{
            "5.34.1":{
               "pass":6
            },
            "5.36.0":{
               "fail":1
            }
         }
      },
      "XML-Rules":{
         "1.16":{
            "5.34.1":{
               "fail":6,
               "pass":5
            },
            "5.36.0":{
               "fail":6
            }
         }
      },
      "XS-TCC":{
         "0.05":{
            "5.34.1":{
               "pass":8
            },
            "5.36.0":{
               "fail":7
            }
         }
      },
      "go-perl":{
         "0.15":{
            "5.34.1":{
               "fail":8,
               "pass":4
            },
            "5.36.0":{
               "fail":6
            }
         }
      },
      "minismokebox":{
         "0.68":{
            "5.34.1":{
               "pass":9
            },
            "5.36.0":{
               "fail":1,
               "pass":10
            }
         }
      },
      "scriptname":{
         "0.92":{
            "5.34.1":{
               "fail":3,
               "pass":2
            },
            "5.36.0":{
               "fail":1
            }
         }
      }
   }
}
