{
   "!ALL":{
      "5.37.9":193481,
      "datetime":"2023-03-14T12:51:49",
      "perls":[
         "5.36.0",
         "5.37.9"
      ],
      "totalrcdists":31144
   },
   "!CAND":{
      "AI-MaxEntropy":{
         "0.20":{
            "5.36.0":{},
            "5.37.9":{
               "fail":3,
               "pass":1
            }
         }
      },
      "Acme-CPANAuthors-French":{
         "0.09":{
            "5.36.0":{
               "fail":26,
               "pass":1
            },
            "5.37.9":{
               "fail":5
            }
         }
      },
      "Acme-Hoge":{
         "0.03":{
            "5.36.0":{
               "fail":3
            },
            "5.37.9":{
               "fail":2,
               "pass":3
            }
         }
      },
      "Acme-MyPeek":{
         "0.07":{
            "5.36.0":{
               "fail":2
            },
            "5.37.9":{
               "fail":1,
               "pass":4
            }
         }
      },
      "Acme-Perl-VM":{
         "0.006":{
            "5.36.0":{
               "fail":7,
               "pass":1
            },
            "5.37.9":{
               "fail":4
            }
         }
      },
      "Acme-Spider":{
         "0.02":{
            "5.36.0":{},
            "5.37.9":{
               "fail":4,
               "pass":1
            }
         }
      },
      "Algorithm-CurveFit":{
         "1.05":{
            "5.36.0":{
               "fail":9,
               "pass":3
            },
            "5.37.9":{
               "fail":6
            }
         }
      },
      "Alien-Bazel":{
         "0.02":{
            "5.36.0":{
               "fail":1,
               "pass":4
            },
            "5.37.9":{
               "fail":5
            }
         }
      },
      "Alien-Kiwisolver":{
         "0.003":{
            "5.36.0":{
               "pass":25
            },
            "5.37.9":{
               "fail":1,
               "pass":5
            }
         }
      },
      "Alien-Leptonica":{
         "0.007":{
            "5.36.0":{
               "fail":3,
               "pass":10
            },
            "5.37.9":{
               "fail":4
            }
         }
      },
      "Alien-Libarchive3":{
         "0.33":{
            "5.36.0":{
               "pass":17
            },
            "5.37.9":{
               "fail":5
            }
         }
      },
      "Alien-ghostunnel":{
         "0.01":{
            "5.36.0":{
               "pass":6
            },
            "5.37.9":{
               "fail":3,
               "pass":2
            }
         }
      },
      "Alien-libdeflate":{
         "0.03":{
            "5.36.0":{
               "fail":7,
               "pass":13
            },
            "5.37.9":{
               "fail":2
            }
         }
      },
      "Angle-Omega":{
         "1.00":{
            "5.36.0":{
               "fail":2,
               "pass":1
            },
            "5.37.9":{
               "fail":5
            }
         }
      },
      "AnyEvent-Discord-Client":{
         "0.000002":{
            "5.36.0":{
               "pass":2
            },
            "5.37.9":{
               "fail":1,
               "pass":3
            }
         }
      },
      "AnyEvent-Redis-RipeRedis":{
         "1.62":{
            "5.36.0":{
               "fail":4,
               "pass":6
            },
            "5.37.9":{
               "fail":4
            }
         }
      },
      "AnyEvent-SMTP":{
         "0.10":{
            "5.36.0":{
               "pass":3
            },
            "5.37.9":{
               "fail":1,
               "pass":6
            }
         }
      },
      "AnyEvent-Yubico":{
         "0.9.3":{
            "5.36.0":{
               "fail":3,
               "pass":5
            },
            "5.37.9":{
               "fail":4
            }
         }
      },
      "Apache-DBI-Cache":{
         "0.08":{
            "5.36.0":{
               "fail":4
            },
            "5.37.9":{
               "fail":2,
               "pass":2
            }
         }
      },
      "Apache-Scriptor":{
         "1.21":{
            "5.36.0":{
               "fail":8
            },
            "5.37.9":{
               "fail":4,
               "pass":1
            }
         }
      },
      "Apache-Scriptor-Simple":{
         "1.21":{
            "5.36.0":{
               "fail":2
            },
            "5.37.9":{
               "fail":3,
               "pass":1
            }
         }
      },
      "Apache-Session-SharedMem":{
         "0.6":{
            "5.36.0":{
               "pass":8
            },
            "5.37.9":{
               "fail":1,
               "pass":4
            }
         }
      },
      "App-ClusterSSH":{
         "4.16":{
            "5.36.0":{
               "fail":2,
               "pass":4
            },
            "5.37.9":{
               "fail":1
            }
         }
      },
      "App-Perl-Module-CopyrightYears":{
         "0.01":{
            "5.36.0":{
               "fail":20,
               "pass":9
            },
            "5.37.9":{
               "fail":1
            }
         },
         "0.02":{
            "5.36.0":{
               "fail":16,
               "pass":9
            },
            "5.37.9":{
               "fail":1
            }
         }
      },
      "App-RetroPAN":{
         "0.03":{
            "5.36.0":{
               "pass":5
            },
            "5.37.9":{
               "fail":2,
               "pass":2
            }
         }
      },
      "App-SCM-Digest":{
         "0.13":{
            "5.36.0":{
               "pass":2
            },
            "5.37.9":{
               "fail":2,
               "pass":2
            }
         }
      },
      "App-Stacktrace":{
         "0.09":{
            "5.36.0":{
               "fail":19,
               "pass":1
            },
            "5.37.9":{
               "fail":5
            }
         }
      },
      "App-assh":{
         "1.1.2":{
            "5.36.0":{
               "fail":2,
               "pass":19
            },
            "5.37.9":{
               "fail":4
            }
         }
      },
      "App-find2perl":{
         "1.005":{
            "5.36.0":{
               "pass":23
            },
            "5.37.9":{
               "fail":4,
               "pass":25
            }
         }
      },
      "App-perlfind":{
         "2.07":{
            "5.36.0":{
               "pass":14
            },
            "5.37.9":{
               "fail":1,
               "pass":3
            }
         }
      },
      "Archive-Tar-Wrapper":{
         "0.38":{
            "5.36.0":{
               "pass":64
            },
            "5.37.9":{
               "fail":7,
               "pass":20
            }
         }
      },
      "Ark-Plugin-Authentication":{
         "0.01":{
            "5.36.0":{
               "fail":3,
               "pass":1
            },
            "5.37.9":{
               "fail":5
            }
         }
      },
      "Array-GroupBy":{
         "v0.0.4":{
            "5.36.0":{
               "fail":4
            },
            "5.37.9":{
               "fail":2,
               "pass":2
            }
         }
      },
      "Array-Ordered":{
         "0.03":{
            "5.36.0":{
               "pass":1
            },
            "5.37.9":{
               "fail":1,
               "pass":3
            }
         }
      },
      "Array-Sticky":{
         "0.01":{
            "5.36.0":{
               "fail":2
            },
            "5.37.9":{
               "fail":4,
               "pass":1
            }
         }
      },
      "Astro-FITS-CFITSIO-Utils":{
         "0.13":{
            "5.36.0":{},
            "5.37.9":{
               "fail":3,
               "pass":1
            }
         }
      },
      "Astro-QDP-Parse":{
         "0.13":{
            "5.36.0":{
               "fail":4
            },
            "5.37.9":{
               "fail":3,
               "pass":1
            }
         }
      },
      "Async-Microservice":{
         "0.02":{
            "5.36.0":{
               "fail":4,
               "pass":4
            },
            "5.37.9":{
               "fail":4
            }
         }
      },
      "Audio-File":{
         "0.11":{
            "5.36.0":{
               "fail":13,
               "pass":2
            },
            "5.37.9":{
               "fail":4
            }
         }
      },
      "B-Deobfuscate":{
         "0.20":{
            "5.36.0":{
               "pass":7
            },
            "5.37.9":{
               "fail":4
            }
         }
      },
      "B-Tree":{
         "0.02":{
            "5.36.0":{
               "pass":2
            },
            "5.37.9":{
               "fail":4,
               "pass":1
            }
         }
      },
      "Backup-Duplicity-YADW":{
         "0.12":{
            "5.36.0":{
               "pass":5
            },
            "5.37.9":{
               "fail":4
            }
         }
      },
      "Bank-Holidays":{
         "0.86":{
            "5.36.0":{
               "pass":2
            },
            "5.37.9":{
               "fail":5
            }
         }
      },
      "Biblio-Citation-Compare":{
         "0.55":{
            "5.36.0":{
               "fail":2,
               "pass":10
            },
            "5.37.9":{
               "fail":1
            }
         }
      },
      "Biblio-Refbase":{
         "0.04":{
            "5.36.0":{
               "fail":12,
               "pass":5
            },
            "5.37.9":{
               "fail":5
            }
         }
      },
      "Bloom16":{
         "0.01":{
            "5.36.0":{
               "pass":1
            },
            "5.37.9":{
               "fail":4
            }
         }
      },
      "Broker-Async":{
         "0.0.6":{
            "5.36.0":{
               "pass":2
            },
            "5.37.9":{
               "fail":1,
               "pass":3
            }
         }
      },
      "Business-CCProcessor":{
         "0.09":{
            "5.36.0":{
               "fail":1,
               "pass":1
            },
            "5.37.9":{
               "fail":4
            }
         }
      },
      "CGI-Application-Plugin-ProtectCSRF":{
         "1.01":{
            "5.36.0":{
               "fail":3,
               "pass":2
            },
            "5.37.9":{
               "fail":4
            }
         }
      },
      "CGI-Getopt":{
         "0.13":{
            "5.36.0":{
               "pass":4
            },
            "5.37.9":{
               "fail":1,
               "pass":4
            }
         }
      },
      "CGI-Info":{
         "0.74":{
            "5.36.0":{
               "pass":26
            },
            "5.37.9":{
               "fail":3,
               "pass":5
            }
         }
      },
      "CGI-Plus":{
         "0.15":{
            "5.36.0":{
               "fail":1,
               "pass":3
            },
            "5.37.9":{
               "fail":4
            }
         }
      },
      "CGI-Session-Driver-memcache":{
         "0.10":{
            "5.36.0":{
               "fail":2,
               "pass":1
            },
            "5.37.9":{
               "fail":4
            }
         }
      },
      "CHI-Driver-SharedMem":{
         "0.14":{
            "5.36.0":{
               "pass":2
            },
            "5.37.9":{
               "fail":1,
               "pass":2
            }
         }
      },
      "CIAO-Lib-StackIO":{
         "0.02":{
            "5.36.0":{
               "pass":1
            },
            "5.37.9":{
               "fail":1,
               "pass":4
            }
         }
      },
      "CPAN-Testers-Reports-Counts":{
         "0.05":{
            "5.36.0":{
               "fail":2
            },
            "5.37.9":{
               "fail":2,
               "pass":3
            }
         }
      },
      "CPANPLUS-Daemon":{
         "0.02":{
            "5.36.0":{
               "pass":1
            },
            "5.37.9":{
               "fail":1,
               "pass":2
            }
         }
      },
      "CPANPLUS-Shell-Default-Plugins-Prereqs":{
         "0.14":{
            "5.36.0":{
               "pass":8
            },
            "5.37.9":{
               "fail":2,
               "pass":2
            }
         }
      },
      "CSS-DOM":{
         "0.17":{
            "5.36.0":{
               "pass":18
            },
            "5.37.9":{
               "fail":7
            }
         }
      },
      "CTM":{
         "0.181":{
            "5.36.0":{
               "pass":3
            },
            "5.37.9":{
               "fail":4
            }
         }
      },
      "Cache-FastMmap":{
         "1.57":{
            "5.36.0":{
               "pass":66
            },
            "5.37.9":{
               "fail":4,
               "pass":31
            }
         }
      },
      "Cache-Profile":{
         "0.06":{
            "5.36.0":{
               "pass":7
            },
            "5.37.9":{
               "fail":1,
               "pass":3
            }
         }
      },
      "Calendar-Model":{
         "0.04":{
            "5.36.0":{
               "pass":4
            },
            "5.37.9":{
               "fail":2,
               "pass":2
            }
         }
      },
      "Cassandra-Lite":{
         "0.4.0":{
            "5.36.0":{
               "fail":12,
               "pass":2
            },
            "5.37.9":{
               "fail":3
            }
         }
      },
      "Catalyst-Authentication-Store-DBIx-Class":{
         "0.1506":{
            "5.36.0":{
               "pass":28
            },
            "5.37.9":{
               "fail":1,
               "pass":20
            }
         }
      },
      "Catalyst-Authentication-Store-FromSub":{
         "0.01":{
            "5.36.0":{
               "fail":5,
               "pass":4
            },
            "5.37.9":{
               "fail":4
            }
         }
      },
      "Catalyst-Authentication-Store-MongoDB":{
         "0.02":{
            "5.36.0":{
               "fail":9,
               "pass":1
            },
            "5.37.9":{
               "fail":4
            }
         }
      },
      "Catalyst-Plugin-Authentication":{
         "0.10023":{
            "5.36.0":{
               "pass":29
            },
            "5.37.9":{
               "fail":4,
               "pass":24
            }
         }
      },
      "Catalyst-Plugin-Authentication-Credential-AOL":{
         "0.02":{
            "5.36.0":{
               "pass":2
            },
            "5.37.9":{
               "fail":1,
               "pass":4
            }
         }
      },
      "Catalyst-Plugin-Cache":{
         "0.12":{
            "5.36.0":{
               "pass":26
            },
            "5.37.9":{
               "fail":1,
               "pass":23
            }
         }
      },
      "Catalyst-Plugin-Charsets-Japanese":{
         "0.06":{
            "5.36.0":{
               "fail":7,
               "pass":1
            },
            "5.37.9":{
               "fail":5
            }
         }
      },
      "Catalyst-Plugin-Session-Store-BerkeleyDB":{
         "0.04":{
            "5.36.0":{
               "fail":9,
               "pass":2
            },
            "5.37.9":{
               "fail":4
            }
         }
      },
      "Catalyst-Plugin-UploadProgress":{
         "0.06":{
            "5.36.0":{
               "pass":3
            },
            "5.37.9":{
               "fail":2,
               "pass":2
            }
         }
      },
      "Catalyst-Runtime":{
         "5.90130":{
            "5.36.0":{
               "pass":26
            },
            "5.37.9":{
               "fail":1,
               "pass":28
            }
         }
      },
      "Catalyst-TraitFor-Request-StructuredParameters":{
         "0.009":{
            "5.36.0":{
               "pass":15
            },
            "5.37.9":{
               "fail":2,
               "pass":2
            }
         }
      },
      "Centrifugo-Client":{
         "1.05":{
            "5.36.0":{
               "fail":1,
               "pass":4
            },
            "5.37.9":{
               "fail":4
            }
         }
      },
      "Class-DBI-Test-TempDB":{
         "1.01":{
            "5.36.0":{
               "pass":3
            },
            "5.37.9":{
               "fail":4,
               "pass":1
            }
         }
      },
      "Class-DataStore":{
         "0.07":{
            "5.36.0":{},
            "5.37.9":{
               "fail":3,
               "pass":2
            }
         }
      },
      "Class-Simple-Cached":{
         "0.04":{
            "5.36.0":{
               "pass":10
            },
            "5.37.9":{
               "fail":4
            }
         }
      },
      "Class-Simple-Readonly-Cached":{
         "0.08":{
            "5.36.0":{
               "pass":11
            },
            "5.37.9":{
               "fail":4
            }
         }
      },
      "Class-Trait":{
         "0.31":{
            "5.36.0":{
               "fail":13,
               "pass":9
            },
            "5.37.9":{
               "fail":5
            }
         }
      },
      "Clipboard":{
         "0.28":{
            "5.36.0":{
               "pass":26
            },
            "5.37.9":{
               "fail":2,
               "pass":4
            }
         }
      },
      "Coerce-Types-Standard":{
         "0.000007":{
            "5.36.0":{
               "fail":25,
               "pass":38
            },
            "5.37.9":{
               "fail":1
            }
         }
      },
      "Config-Properties-Commons":{
         "v1.0.1":{
            "5.36.0":{
               "pass":3
            },
            "5.37.9":{
               "fail":4
            }
         }
      },
      "Convert-Bencode_XS":{
         "0.06":{
            "5.36.0":{
               "fail":25,
               "pass":7
            },
            "5.37.9":{
               "fail":7
            }
         }
      },
      "Coro":{
         "6.57":{
            "5.36.0":{
               "pass":36
            },
            "5.37.9":{
               "fail":3,
               "pass":15
            }
         }
      },
      "Crypt-GCM":{
         "0.02":{
            "5.36.0":{
               "pass":2
            },
            "5.37.9":{
               "fail":1,
               "pass":4
            }
         }
      },
      "Crypt-HSXKPasswd":{
         "v3.6":{
            "5.36.0":{
               "fail":11,
               "pass":6
            },
            "5.37.9":{
               "fail":4
            }
         }
      },
      "Crypt-OpenSSL-Blowfish-CFB64":{
         "0.01":{
            "5.36.0":{
               "pass":3
            },
            "5.37.9":{
               "fail":3,
               "pass":25
            }
         }
      },
      "Crypt-OpenSSL-Random":{
         "0.15":{
            "5.36.0":{
               "pass":85
            },
            "5.37.9":{
               "fail":3,
               "pass":36
            }
         }
      },
      "Crypt-OpenSSL-X509":{
         "1.914":{
            "5.36.0":{
               "pass":75
            },
            "5.37.9":{
               "fail":3,
               "pass":34
            }
         }
      },
      "Crypt-SSLeay":{
         "0.72":{
            "5.36.0":{
               "fail":27,
               "pass":1
            },
            "5.37.9":{
               "fail":6
            }
         }
      },
      "DBIx-ActiveRecord":{
         "0.03":{
            "5.36.0":{
               "fail":3
            },
            "5.37.9":{
               "fail":2,
               "pass":2
            }
         }
      },
      "DBIx-AssertIndex":{
         "0.02":{
            "5.36.0":{
               "pass":4
            },
            "5.37.9":{
               "fail":2,
               "pass":2
            }
         }
      },
      "DBIx-Class-Indexer-WebService-Dezi":{
         "0.08":{
            "5.36.0":{
               "pass":1
            },
            "5.37.9":{
               "fail":1,
               "pass":3
            }
         }
      },
      "DBIx-Handler-Sunny":{
         "0.02":{
            "5.36.0":{
               "pass":5
            },
            "5.37.9":{
               "fail":2,
               "pass":2
            }
         }
      },
      "DBIx-Inspector":{
         "0.12":{
            "5.36.0":{
               "pass":29
            },
            "5.37.9":{
               "fail":6
            }
         }
      },
      "DBIx-QueryByName":{
         "0.18":{
            "5.36.0":{
               "fail":16,
               "pass":1
            },
            "5.37.9":{
               "fail":3
            }
         }
      },
      "DBIx-SchemaChecksum":{
         "1.104":{
            "5.36.0":{
               "pass":2
            },
            "5.37.9":{
               "fail":5
            }
         }
      },
      "DBIx-Tree-MaterializedPath":{
         "v0.06":{
            "5.36.0":{
               "fail":1
            },
            "5.37.9":{
               "fail":2,
               "pass":2
            }
         }
      },
      "DBM-Deep":{
         "2.0016":{
            "5.36.0":{
               "pass":65
            },
            "5.37.9":{
               "fail":33,
               "pass":16
            }
         }
      },
      "Dancer-Plugin-Auth-Krb5":{
         "0.02":{
            "5.36.0":{
               "pass":2
            },
            "5.37.9":{
               "fail":4
            }
         }
      },
      "Dancer-Plugin-FormattedOutput":{
         "0.01":{
            "5.36.0":{
               "pass":7
            },
            "5.37.9":{
               "fail":4
            }
         }
      },
      "Data-AMF":{
         "0.09":{
            "5.36.0":{
               "fail":17,
               "pass":7
            },
            "5.37.9":{
               "fail":6
            }
         }
      },
      "Data-Clone":{
         "0.004":{
            "5.36.0":{
               "pass":71
            },
            "5.37.9":{
               "fail":34,
               "pass":13
            }
         }
      },
      "Data-Dump-Streamer":{
         "2.42":{
            "5.36.0":{
               "pass":22
            },
            "5.37.9":{
               "fail":1,
               "pass":13
            }
         }
      },
      "Data-Dump-XML":{
         "1.19":{
            "5.36.0":{
               "fail":16,
               "pass":1
            },
            "5.37.9":{
               "fail":5
            }
         }
      },
      "Data-Fax":{
         "0.02":{
            "5.36.0":{
               "fail":7
            },
            "5.37.9":{
               "fail":1,
               "pass":3
            }
         }
      },
      "Data-Feed":{
         "0.00015":{
            "5.36.0":{
               "pass":5
            },
            "5.37.9":{
               "fail":5
            }
         }
      },
      "Data-Iter":{
         "0.2":{
            "5.36.0":{
               "fail":9,
               "pass":3
            },
            "5.37.9":{
               "fail":4
            }
         }
      },
      "Data-Object":{
         "2.05":{
            "5.36.0":{
               "pass":6
            },
            "5.37.9":{
               "fail":6
            }
         }
      },
      "Data-Object-Role":{
         "2.01":{
            "5.36.0":{
               "fail":1,
               "pass":6
            },
            "5.37.9":{
               "fail":6
            }
         }
      },
      "Data-Pensieve":{
         "0.03a":{
            "5.36.0":{
               "fail":3
            },
            "5.37.9":{
               "fail":3,
               "pass":2
            }
         }
      },
      "Data-Resolver":{
         "0.003-TRIAL":{
            "5.36.0":{
               "fail":9,
               "pass":1
            },
            "5.37.9":{
               "fail":2
            }
         }
      },
      "Data-Sah":{
         "0.914":{
            "5.36.0":{
               "pass":22
            },
            "5.37.9":{
               "fail":2,
               "pass":5
            }
         }
      },
      "Data-Sah-JS":{
         "0.87":{
            "5.36.0":{
               "fail":15,
               "pass":26
            },
            "5.37.9":{
               "fail":3
            }
         }
      },
      "Database-DumpTruck":{
         "1.2":{
            "5.36.0":{
               "pass":4
            },
            "5.37.9":{
               "fail":5
            }
         }
      },
      "Date-Extract-PERLANCAR":{
         "0.002":{
            "5.36.0":{
               "fail":1,
               "pass":7
            },
            "5.37.9":{
               "fail":6
            }
         }
      },
      "DateStamp":{
         "v1.0.4":{
            "5.36.0":{},
            "5.37.9":{
               "fail":2,
               "pass":4
            }
         }
      },
      "DateTime-Calendar-Coptic":{
         "0.03":{
            "5.36.0":{
               "pass":6
            },
            "5.37.9":{
               "fail":1,
               "pass":3
            }
         }
      },
      "DateTime-Ordinal":{
         "0.04":{
            "5.36.0":{
               "pass":6
            },
            "5.37.9":{
               "fail":4
            }
         }
      },
      "DateTime-Tiny":{
         "1.07":{
            "5.36.0":{
               "fail":21,
               "pass":20
            },
            "5.37.9":{
               "fail":33
            }
         }
      },
      "DateTimeX-Moment":{
         "0.06":{
            "5.36.0":{
               "fail":4,
               "pass":10
            },
            "5.37.9":{
               "fail":5
            }
         }
      },
      "Debug-EchoMessage":{
         "1.03":{
            "5.36.0":{
               "pass":1
            },
            "5.37.9":{
               "fail":1,
               "pass":3
            }
         }
      },
      "Debug-LTrace":{
         "0.03":{
            "5.36.0":{
               "fail":3
            },
            "5.37.9":{
               "fail":3,
               "pass":2
            }
         }
      },
      "Desktop-Notify":{
         "0.05":{
            "5.36.0":{
               "fail":16,
               "pass":5
            },
            "5.37.9":{
               "fail":5
            }
         }
      },
      "Devel-Caller":{
         "2.06":{
            "5.36.0":{
               "pass":119
            },
            "5.37.9":{
               "fail":45
            }
         }
      },
      "Devel-Command-NewF":{
         "0.02":{
            "5.36.0":{
               "fail":4
            },
            "5.37.9":{
               "fail":3,
               "pass":1
            }
         }
      },
      "Devel-Cover":{
         "1.38":{
            "5.36.0":{
               "pass":60
            },
            "5.37.9":{
               "fail":35
            }
         }
      },
      "Devel-Debug-DBGp":{
         "0.22":{
            "5.36.0":{
               "pass":5
            },
            "5.37.9":{
               "fail":5
            }
         }
      },
      "Devel-ModInfo":{
         "2.04":{
            "5.36.0":{
               "fail":10,
               "pass":1
            },
            "5.37.9":{
               "fail":4
            }
         }
      },
      "Devel-NYTProf-Callgrind-TicksDiff":{
         "0.05":{
            "5.36.0":{
               "fail":1
            },
            "5.37.9":{
               "fail":2,
               "pass":2
            }
         }
      },
      "Devel-PrettyTrace":{
         "0.07":{
            "5.36.0":{
               "pass":6
            },
            "5.37.9":{
               "fail":4
            }
         }
      },
      "Devel-PtrTable":{
         "0.03":{
            "5.36.0":{
               "fail":1
            },
            "5.37.9":{
               "fail":1,
               "pass":1
            }
         }
      },
      "Devel-RingBuffer":{
         "0.31":{
            "5.36.0":{
               "fail":6,
               "pass":2
            },
            "5.37.9":{
               "fail":4
            }
         }
      },
      "Devel-WatchVars":{
         "v1.0.5":{
            "5.36.0":{
               "pass":12
            },
            "5.37.9":{
               "fail":4
            }
         }
      },
      "Devel-bt":{
         "0.06":{
            "5.36.0":{
               "fail":5,
               "pass":12
            },
            "5.37.9":{
               "fail":4
            }
         }
      },
      "Device-Chip-BV4243":{
         "0.03":{
            "5.36.0":{
               "pass":2
            },
            "5.37.9":{
               "fail":5
            }
         }
      },
      "Device-Chip-SDCard":{
         "0.03":{
            "5.36.0":{
               "pass":4
            },
            "5.37.9":{
               "fail":4
            }
         }
      },
      "Digest-BLAKE2":{
         "0.02":{
            "5.36.0":{
               "pass":3
            },
            "5.37.9":{
               "fail":1,
               "pass":2
            }
         }
      },
      "Digest-OAT":{
         "0.04":{
            "5.36.0":{
               "pass":19
            },
            "5.37.9":{
               "fail":6,
               "pass":1
            }
         }
      },
      "Dist-Surveyor":{
         "0.021":{
            "5.36.0":{},
            "5.37.9":{
               "fail":1,
               "pass":4
            }
         }
      },
      "Dist-Zilla-Plugin-BumpVersionFromGit":{
         "0.010":{
            "5.36.0":{
               "pass":17
            },
            "5.37.9":{
               "fail":1,
               "pass":4
            }
         }
      },
      "Dist-Zilla-Plugin-LaunchpadPPA":{
         "0.1":{
            "5.36.0":{
               "fail":6,
               "pass":1
            },
            "5.37.9":{
               "fail":4
            }
         }
      },
      "Dist-Zilla-Tester-DieHard":{
         "v0.6.4":{
            "5.36.0":{
               "pass":17
            },
            "5.37.9":{
               "fail":6
            }
         }
      },
      "Doit":{
         "0.026":{
            "5.36.0":{
               "pass":43
            },
            "5.37.9":{
               "fail":4,
               "pass":1
            }
         }
      },
      "Email-Template":{
         "0.02":{
            "5.36.0":{
               "fail":1,
               "pass":5
            },
            "5.37.9":{
               "fail":4
            }
         }
      },
      "ExtUtils-HasCompiler":{
         "0.023":{
            "5.36.0":{
               "pass":8
            },
            "5.37.9":{
               "fail":3,
               "pass":26
            }
         }
      },
      "FCGI-Async":{
         "0.22":{
            "5.36.0":{
               "pass":13
            },
            "5.37.9":{
               "fail":1,
               "pass":4
            }
         }
      },
      "FFI-Me":{
         "0.01":{
            "5.36.0":{
               "pass":5
            },
            "5.37.9":{
               "fail":3,
               "pass":11
            }
         }
      },
      "FFI-Raw":{
         "0.32":{
            "5.36.0":{
               "pass":16
            },
            "5.37.9":{
               "fail":13,
               "pass":17
            }
         }
      },
      "FTN-Crypt":{
         "0.5":{
            "5.36.0":{
               "fail":6,
               "pass":1
            },
            "5.37.9":{
               "fail":5
            }
         }
      },
      "Faker":{
         "1.17":{
            "5.36.0":{
               "fail":22,
               "pass":25
            },
            "5.37.9":{
               "fail":5
            }
         }
      },
      "File-Copy-Recursive":{
         "0.45":{
            "5.36.0":{
               "pass":84
            },
            "5.37.9":{
               "fail":4,
               "pass":30
            }
         }
      },
      "File-List-Object":{
         "0.202":{
            "5.36.0":{
               "fail":3,
               "pass":5
            },
            "5.37.9":{
               "fail":5
            }
         }
      },
      "File-Path-Tiny":{
         "1.0":{
            "5.36.0":{
               "pass":45
            },
            "5.37.9":{
               "fail":4,
               "pass":27
            }
         }
      },
      "File-Tail-Dir":{
         "0.16":{
            "5.36.0":{
               "fail":4,
               "pass":8
            },
            "5.37.9":{
               "fail":5
            }
         }
      },
      "File-Touch":{
         "0.12":{
            "5.36.0":{
               "pass":74
            },
            "5.37.9":{
               "fail":4,
               "pass":26
            }
         }
      },
      "Filesys-Type":{
         "0.02":{
            "5.36.0":{
               "fail":2,
               "pass":9
            },
            "5.37.9":{
               "fail":5
            }
         }
      },
      "Finance-Bank-Commerzbank":{
         "0.29":{
            "5.36.0":{
               "pass":2
            },
            "5.37.9":{
               "fail":1,
               "pass":4
            }
         }
      },
      "Finance-Libdogecoin":{
         "1.20220815.1712":{
            "5.36.0":{
               "pass":15
            },
            "5.37.9":{
               "fail":1,
               "pass":3
            }
         }
      },
      "Finance-TA":{
         "v0.4.3":{
            "5.36.0":{
               "fail":2
            },
            "5.37.9":{
               "fail":1,
               "pass":4
            }
         }
      },
      "Footprintless-Plugin-Atlassian-Confluence":{
         "1.03":{
            "5.36.0":{
               "pass":4
            },
            "5.37.9":{
               "fail":1,
               "pass":5
            }
         }
      },
      "FrameMaker-MifTree":{
         "0.075":{
            "5.36.0":{
               "fail":1
            },
            "5.37.9":{
               "fail":1,
               "pass":3
            }
         }
      },
      "FunctionalPerl":{
         "0.72.76":{
            "5.36.0":{
               "pass":30
            },
            "5.37.9":{
               "fail":4
            }
         }
      },
      "Games-AssaultCube":{
         "0.04":{
            "5.36.0":{
               "pass":8
            },
            "5.37.9":{
               "fail":4
            }
         }
      },
      "Games-Messages":{
         "0.05":{
            "5.36.0":{
               "fail":3
            },
            "5.37.9":{
               "fail":3,
               "pass":1
            }
         }
      },
      "GearmanX-Worker":{
         "0.02":{
            "5.36.0":{
               "pass":1
            },
            "5.37.9":{
               "fail":2,
               "pass":2
            }
         }
      },
      "Geo-Coder-CA":{
         "0.13":{
            "5.36.0":{
               "fail":21,
               "pass":1
            },
            "5.37.9":{
               "fail":4
            }
         }
      },
      "Geo-Coder-GeocodeFarm":{
         "0.0402":{
            "5.36.0":{
               "pass":14
            },
            "5.37.9":{
               "fail":1,
               "pass":3
            }
         }
      },
      "Geo-Coder-GoogleMaps":{
         "0.4":{
            "5.36.0":{
               "fail":3
            },
            "5.37.9":{
               "fail":3,
               "pass":2
            }
         }
      },
      "Geo-Google-PolylineEncoder":{
         "0.06":{
            "5.36.0":{
               "fail":1,
               "pass":1
            },
            "5.37.9":{
               "fail":4
            }
         }
      },
      "Geo-GoogleEarth-AutoTour":{
         "1.08":{
            "5.36.0":{
               "fail":3,
               "pass":14
            },
            "5.37.9":{
               "fail":4
            }
         }
      },
      "Geo-Index":{
         "v0.0.8":{
            "5.36.0":{
               "fail":2,
               "pass":1
            },
            "5.37.9":{
               "fail":4
            }
         }
      },
      "Geo-OSM-DBI":{
         "0.01":{
            "5.36.0":{
               "fail":1
            },
            "5.37.9":{
               "fail":2,
               "pass":3
            }
         }
      },
      "GitInsight":{
         "0.06":{
            "5.36.0":{
               "fail":3,
               "pass":1
            },
            "5.37.9":{
               "fail":5
            }
         }
      },
      "Google-ProtocolBuffers-Dynamic":{
         "0.41_15":{
            "5.36.0":{
               "pass":2
            },
            "5.37.9":{
               "fail":3
            }
         }
      },
      "Gpx-Addons-Filter":{
         "0.04":{
            "5.36.0":{
               "fail":10,
               "pass":6
            },
            "5.37.9":{
               "fail":4
            }
         }
      },
      "Graph-Maker":{
         "0.02":{
            "5.36.0":{
               "fail":11,
               "pass":17
            },
            "5.37.9":{
               "fail":5
            }
         }
      },
      "Gtk2":{
         "1.24993":{
            "5.36.0":{
               "fail":23,
               "pass":6
            },
            "5.37.9":{
               "fail":6
            }
         }
      },
      "HAM-Device-IcomCIV":{
         "0.02":{
            "5.36.0":{
               "fail":2
            },
            "5.37.9":{
               "fail":3,
               "pass":1
            }
         }
      },
      "HTML-Blitz":{
         "0.06":{
            "5.36.0":{
               "pass":16
            },
            "5.37.9":{
               "fail":5
            }
         }
      },
      "HTML-ExtractContent":{
         "0.12":{
            "5.36.0":{
               "pass":16
            },
            "5.37.9":{
               "fail":2,
               "pass":4
            }
         }
      },
      "HTML-Laundry":{
         "0.0107":{
            "5.36.0":{
               "fail":5,
               "pass":6
            },
            "5.37.9":{
               "fail":5
            }
         }
      },
      "HTML-Mason":{
         "1.59":{
            "5.36.0":{
               "pass":46
            },
            "5.37.9":{
               "fail":18
            }
         }
      },
      "HTML-RSSAutodiscovery":{
         "1.21":{
            "5.36.0":{
               "fail":2
            },
            "5.37.9":{
               "fail":3,
               "pass":1
            }
         }
      },
      "HTML-Template-Dumper":{
         "0.1":{
            "5.36.0":{
               "fail":3
            },
            "5.37.9":{
               "fail":3,
               "pass":1
            }
         }
      },
      "HTML-WidgetValidator":{
         "0.0.3":{
            "5.36.0":{
               "pass":5
            },
            "5.37.9":{
               "fail":4,
               "pass":1
            }
         }
      },
      "HTML-XHTML-DVSM":{
         "1.2":{
            "5.36.0":{
               "fail":7,
               "pass":1
            },
            "5.37.9":{
               "fail":4
            }
         }
      },
      "HTTP-Proxy":{
         "0.304":{
            "5.36.0":{
               "fail":1
            },
            "5.37.9":{
               "fail":1,
               "pass":1
            }
         }
      },
      "HTTP-Request-FromLog":{
         "0.00002":{
            "5.36.0":{
               "fail":10,
               "pass":8
            },
            "5.37.9":{
               "fail":4
            }
         }
      },
      "HTTP-Size":{
         "1.153":{
            "5.36.0":{
               "pass":5
            },
            "5.37.9":{
               "fail":1,
               "pass":5
            }
         }
      },
      "Hardware-Vhdl-Tidy":{
         "0.8":{
            "5.36.0":{
               "pass":2
            },
            "5.37.9":{
               "fail":1,
               "pass":3
            }
         }
      },
      "Hoppy":{
         "0.01005":{
            "5.36.0":{
               "fail":4
            },
            "5.37.9":{
               "fail":2,
               "pass":1
            }
         }
      },
      "IMDB-JSON":{
         "0.05":{
            "5.36.0":{
               "fail":8,
               "pass":2
            },
            "5.37.9":{
               "fail":5
            }
         }
      },
      "IO-Buffered":{
         "1.00":{
            "5.36.0":{
               "fail":2,
               "pass":5
            },
            "5.37.9":{
               "fail":2
            }
         }
      },
      "IPC-Shm-Simple":{
         "1.10":{
            "5.36.0":{
               "pass":4
            },
            "5.37.9":{
               "fail":1,
               "pass":3
            }
         }
      },
      "IRC-Indexer":{
         "0.06":{
            "5.36.0":{
               "fail":7,
               "pass":3
            },
            "5.37.9":{
               "fail":3
            }
         }
      },
      "IS-Init":{
         "0.93":{
            "5.36.0":{
               "fail":3
            },
            "5.37.9":{
               "fail":1,
               "pass":3
            }
         }
      },
      "Image-Magick-Safer":{
         "0.07":{
            "5.36.0":{},
            "5.37.9":{
               "fail":2,
               "pass":2
            }
         }
      },
      "Image-Magick-Thumbnail-Simple":{
         "0.12":{
            "5.36.0":{
               "fail":2
            },
            "5.37.9":{
               "fail":2,
               "pass":3
            }
         }
      },
      "Inline-CPP":{
         "0.80":{
            "5.36.0":{
               "pass":47
            },
            "5.37.9":{
               "fail":8,
               "pass":22
            }
         }
      },
      "Inline-Select":{
         "0.01":{
            "5.36.0":{
               "pass":2
            },
            "5.37.9":{
               "fail":1,
               "pass":4
            }
         }
      },
      "JSON-DWIW":{
         "0.47":{
            "5.36.0":{
               "pass":17
            },
            "5.37.9":{
               "fail":1,
               "pass":29
            }
         }
      },
      "JSON-HPack":{
         "0.0.3":{
            "5.36.0":{
               "fail":3
            },
            "5.37.9":{
               "fail":3,
               "pass":1
            }
         }
      },
      "JavaScript-Code":{
         "0.08":{
            "5.36.0":{
               "pass":2
            },
            "5.37.9":{
               "fail":4,
               "pass":1
            }
         }
      },
      "JavaScript-DebugConsole":{
         "0.01":{
            "5.36.0":{
               "fail":1
            },
            "5.37.9":{
               "fail":2,
               "pass":2
            }
         }
      },
      "JavaScript-Duktape":{
         "2.5.0":{
            "5.36.0":{
               "pass":12
            },
            "5.37.9":{
               "fail":1,
               "pass":3
            }
         }
      },
      "JavaScript-Ectype":{
         "0.01":{
            "5.36.0":{
               "fail":6
            },
            "5.37.9":{
               "fail":4,
               "pass":1
            }
         }
      },
      "Kwiki-DB":{
         "0.02":{
            "5.36.0":{
               "fail":6,
               "pass":4
            },
            "5.37.9":{
               "fail":5
            }
         }
      },
      "Kwiki-PageInclude":{
         "0.02":{
            "5.36.0":{
               "pass":1
            },
            "5.37.9":{
               "fail":2,
               "pass":4
            }
         }
      },
      "Kwiki-QuickWAFL":{
         "0.02":{
            "5.36.0":{
               "pass":1
            },
            "5.37.9":{
               "fail":1,
               "pass":4
            }
         }
      },
      "LWP-Curl":{
         "0.14":{
            "5.36.0":{
               "fail":7,
               "pass":8
            },
            "5.37.9":{
               "fail":2
            }
         }
      },
      "LaTeXML-Plugin-latexmls":{
         "1.5":{
            "5.36.0":{
               "fail":2,
               "pass":9
            },
            "5.37.9":{
               "fail":4
            }
         }
      },
      "Lemonldap-NG-Handler":{
         "2.0.16":{
            "5.36.0":{
               "pass":10
            },
            "5.37.9":{
               "fail":5
            }
         }
      },
      "Lingua-Norms-SUBTLEX":{
         "0.07":{
            "5.36.0":{
               "fail":1,
               "pass":2
            },
            "5.37.9":{
               "fail":4
            }
         }
      },
      "Lingua-RU-Numeral":{
         "0.03":{
            "5.36.0":{
               "fail":9,
               "pass":11
            },
            "5.37.9":{
               "fail":1
            }
         }
      },
      "Lingua-RU-Translit":{
         "0.02":{
            "5.36.0":{
               "pass":10
            },
            "5.37.9":{
               "fail":4
            }
         }
      },
      "Lingua-ZH-PinyinConvert":{
         "0.05":{
            "5.36.0":{
               "fail":3
            },
            "5.37.9":{
               "fail":2,
               "pass":2
            }
         }
      },
      "Linux-loadavg":{
         "0.09":{
            "5.36.0":{
               "fail":2
            },
            "5.37.9":{
               "fail":2,
               "pass":2
            }
         }
      },
      "List-Helpers-XS":{
         "0.19":{
            "5.36.0":{
               "pass":1
            },
            "5.37.9":{
               "fail":2,
               "pass":2
            }
         }
      },
      "List-Keywords":{
         "0.09":{
            "5.36.0":{
               "pass":17
            },
            "5.37.9":{
               "fail":1,
               "pass":2
            }
         },
         "0.10":{
            "5.36.0":{
               "pass":19
            },
            "5.37.9":{
               "fail":1,
               "pass":19
            }
         }
      },
      "Locale-Hebrew":{
         "1.05":{
            "5.36.0":{
               "pass":15
            },
            "5.37.9":{
               "fail":5
            }
         }
      },
      "Locale-Hebrew-Calendar":{
         "0.03":{
            "5.36.0":{
               "fail":2,
               "pass":1
            },
            "5.37.9":{
               "fail":4
            }
         }
      },
      "Locale-Maketext-Utils":{
         "0.42":{
            "5.36.0":{
               "fail":6,
               "pass":24
            },
            "5.37.9":{
               "fail":25
            }
         }
      },
      "Log-Declare":{
         "0.10":{
            "5.36.0":{
               "pass":4
            },
            "5.37.9":{
               "fail":1,
               "pass":3
            }
         }
      },
      "Log-FileSimple":{
         "0.02":{
            "5.36.0":{
               "pass":2
            },
            "5.37.9":{
               "fail":2,
               "pass":2
            }
         }
      },
      "Log-QnD":{
         "0.17":{
            "5.36.0":{
               "pass":5
            },
            "5.37.9":{
               "fail":4
            }
         }
      },
      "Logfile-Read":{
         "0.6":{
            "5.36.0":{
               "pass":12
            },
            "5.37.9":{
               "fail":4
            }
         }
      },
      "Logfile-Tail":{
         "0.7":{
            "5.36.0":{
               "pass":4
            },
            "5.37.9":{
               "fail":4
            }
         }
      },
      "MIME-Signature":{
         "0.22":{
            "5.36.0":{
               "pass":7
            },
            "5.37.9":{
               "fail":6
            }
         }
      },
      "MLDBM-Easy":{
         "0.01":{
            "5.36.0":{
               "pass":2
            },
            "5.37.9":{
               "fail":1,
               "pass":4
            }
         }
      },
      "Mail-DMARC":{
         "1.20230215":{
            "5.36.0":{
               "pass":20
            },
            "5.37.9":{
               "fail":1,
               "pass":2
            }
         }
      },
      "Mail-FilterXML":{
         "0.3":{
            "5.36.0":{
               "pass":2
            },
            "5.37.9":{
               "fail":1,
               "pass":3
            }
         }
      },
      "Mail-SPF":{
         "v2.9.0":{
            "5.36.0":{
               "fail":25,
               "pass":11
            },
            "5.37.9":{
               "fail":7
            }
         }
      },
      "Markup-MatchTree":{
         "1.0.0":{
            "5.36.0":{
               "fail":2
            },
            "5.37.9":{
               "fail":3,
               "pass":2
            }
         }
      },
      "MassSpec-ViewSpectrum-RealVsHypPeptide":{
         "0.02":{
            "5.36.0":{
               "fail":3
            },
            "5.37.9":{
               "fail":3,
               "pass":1
            }
         }
      },
      "Math-Complex_C-L":{
         "0.08":{
            "5.36.0":{
               "pass":9
            },
            "5.37.9":{
               "fail":4,
               "pass":20
            }
         }
      },
      "Math-FastGF2":{
         "0.07":{
            "5.36.0":{
               "pass":13
            },
            "5.37.9":{
               "fail":4
            }
         }
      },
      "Math-Formula":{
         "0.10":{
            "5.36.0":{
               "pass":18
            },
            "5.37.9":{
               "fail":1
            }
         },
         "0.13":{
            "5.36.0":{
               "pass":12
            },
            "5.37.9":{
               "fail":5
            }
         },
         "0.14":{
            "5.36.0":{
               "fail":3,
               "pass":9
            },
            "5.37.9":{
               "fail":5
            }
         },
         "0.15":{
            "5.36.0":{
               "fail":2,
               "pass":14
            },
            "5.37.9":{
               "fail":3
            }
         }
      },
      "Math-GMatrix":{
         "0.2":{
            "5.36.0":{
               "pass":4
            },
            "5.37.9":{
               "fail":1,
               "pass":3
            }
         }
      },
      "Math-LongDouble":{
         "0.23":{
            "5.36.0":{
               "pass":14
            },
            "5.37.9":{
               "fail":8,
               "pass":20
            }
         }
      },
      "Math-Pari":{
         "2.030523":{
            "5.36.0":{
               "pass":65
            },
            "5.37.9":{
               "fail":1,
               "pass":12
            }
         }
      },
      "Math-Symbolic-Custom-CCompiler":{
         "1.04":{
            "5.36.0":{
               "pass":4
            },
            "5.37.9":{
               "fail":1,
               "pass":3
            }
         }
      },
      "Media-Convert":{
         "1.0.4":{
            "5.36.0":{
               "fail":10
            },
            "5.37.9":{
               "fail":5,
               "pass":1
            }
         }
      },
      "Memo32":{
         "1.01b":{
            "5.36.0":{
               "pass":2
            },
            "5.37.9":{
               "fail":1,
               "pass":4
            }
         }
      },
      "Module-CoreList":{
         "5.20230120":{
            "5.36.0":{
               "pass":58
            },
            "5.37.9":{
               "fail":5
            }
         }
      },
      "Module-Mask-Deps":{
         "0.07":{
            "5.36.0":{
               "pass":2
            },
            "5.37.9":{
               "fail":2,
               "pass":2
            }
         }
      },
      "Module-Pluggable-Dependency":{
         "0.0.4":{
            "5.36.0":{
               "pass":2
            },
            "5.37.9":{
               "fail":1,
               "pass":3
            }
         }
      },
      "Module-Reader":{
         "0.003003":{
            "5.36.0":{
               "pass":13
            },
            "5.37.9":{
               "fail":4
            }
         }
      },
      "Mojo-AsyncAwait":{
         "0.03":{
            "5.36.0":{
               "fail":4
            },
            "5.37.9":{
               "fail":3,
               "pass":1
            }
         }
      },
      "Mojo-DB-Results-Role-Struct":{
         "v0.1.1":{
            "5.36.0":{
               "pass":3
            },
            "5.37.9":{
               "fail":5
            }
         }
      },
      "Mojo-IOLoop-ReadWriteFork":{
         "2.02":{
            "5.36.0":{
               "pass":51
            },
            "5.37.9":{
               "fail":4,
               "pass":25
            }
         }
      },
      "Mojo-Promise-Role-Futurify":{
         "v1.0.1":{
            "5.36.0":{
               "pass":6
            },
            "5.37.9":{
               "fail":2,
               "pass":3
            }
         }
      },
      "Mojo-UserAgent-Mockable":{
         "1.59":{
            "5.36.0":{
               "fail":15,
               "pass":3
            },
            "5.37.9":{
               "fail":5
            }
         }
      },
      "Mojo-UserAgent-SecureServer":{
         "0.04":{
            "5.36.0":{
               "fail":1,
               "pass":2
            },
            "5.37.9":{
               "fail":4
            }
         }
      },
      "MojoX-JSON-RPC-Service-AutoRegister":{
         "0.001":{
            "5.36.0":{
               "fail":2
            },
            "5.37.9":{
               "fail":4,
               "pass":1
            }
         }
      },
      "Mojolicious-Plugin-DBI":{
         "0.0.1":{
            "5.36.0":{
               "pass":2
            },
            "5.37.9":{
               "fail":1,
               "pass":3
            }
         }
      },
      "Mojolicious-Plugin-Future":{
         "0.002":{
            "5.36.0":{
               "pass":3
            },
            "5.37.9":{
               "fail":2,
               "pass":2
            }
         }
      },
      "Mojolicious-Plugin-OpenAPI-Modern":{
         "0.004":{
            "5.36.0":{
               "fail":1,
               "pass":18
            },
            "5.37.9":{
               "fail":2
            }
         }
      },
      "Mojolicious-Plugin-RedisSubscriber":{
         "0.0.1":{
            "5.36.0":{
               "fail":6,
               "pass":1
            },
            "5.37.9":{
               "fail":4
            }
         }
      },
      "Mojolicious-Plugin-RenderCGI":{
         "0.102":{
            "5.36.0":{
               "pass":10
            },
            "5.37.9":{
               "fail":5
            }
         }
      },
      "Mojolicious-Plugin-ReplyTable":{
         "0.12":{
            "5.36.0":{
               "pass":2
            },
            "5.37.9":{
               "fail":4
            }
         }
      },
      "Moonshine-Util":{
         "0.08":{
            "5.36.0":{
               "fail":10,
               "pass":5
            },
            "5.37.9":{
               "fail":5
            }
         }
      },
      "MooseX-PDF":{
         "0.01":{
            "5.36.0":{
               "fail":4,
               "pass":1
            },
            "5.37.9":{
               "fail":4
            }
         }
      },
      "Moove":{
         "0.006":{
            "5.36.0":{
               "fail":7,
               "pass":8
            },
            "5.37.9":{
               "fail":4
            }
         }
      },
      "Music-Tag":{
         "0.4103":{
            "5.36.0":{
               "fail":1,
               "pass":5
            },
            "5.37.9":{
               "fail":3
            }
         }
      },
      "MyConText":{
         "0.49":{
            "5.36.0":{
               "fail":4
            },
            "5.37.9":{
               "fail":2,
               "pass":2
            }
         }
      },
      "NIST-NVD":{
         "1.02.01":{
            "5.36.0":{
               "fail":1,
               "pass":13
            },
            "5.37.9":{
               "fail":5
            }
         }
      },
      "Nagios-Cmd":{
         "0.05":{
            "5.36.0":{
               "pass":11
            },
            "5.37.9":{
               "fail":4
            }
         }
      },
      "Narada":{
         "v2.3.8":{
            "5.36.0":{
               "pass":5
            },
            "5.37.9":{
               "fail":3,
               "pass":2
            }
         }
      },
      "Nefarious":{
         "0.01":{
            "5.36.0":{
               "fail":13,
               "pass":1
            },
            "5.37.9":{
               "fail":1
            }
         }
      },
      "Net-AS2":{
         "1.0110":{
            "5.36.0":{
               "pass":5
            },
            "5.37.9":{
               "fail":6
            }
         }
      },
      "Net-Amazon-DynamoDB-Table":{
         "0.05":{
            "5.36.0":{
               "pass":5
            },
            "5.37.9":{
               "fail":5
            }
         }
      },
      "Net-Async-Blockchain":{
         "0.002":{
            "5.36.0":{
               "pass":7
            },
            "5.37.9":{
               "fail":1,
               "pass":3
            }
         }
      },
      "Net-IMAP-Server":{
         "1.39":{
            "5.36.0":{
               "fail":4,
               "pass":15
            },
            "5.37.9":{
               "fail":2
            }
         }
      },
      "Net-IP-Route-Reject":{
         "0.5":{
            "5.36.0":{
               "fail":10,
               "pass":2
            },
            "5.37.9":{
               "fail":5
            }
         }
      },
      "Net-IPA":{
         "1.0":{
            "5.36.0":{
               "fail":3
            },
            "5.37.9":{
               "fail":5,
               "pass":1
            }
         }
      },
      "Net-ISC-DHCPd":{
         "0.1709":{
            "5.36.0":{
               "pass":13
            },
            "5.37.9":{
               "fail":1,
               "pass":5
            }
         }
      },
      "Net-Int-Stats":{
         "2.1":{
            "5.36.0":{
               "fail":2
            },
            "5.37.9":{
               "fail":2,
               "pass":2
            }
         }
      },
      "Net-Lyskom":{
         "1.2":{
            "5.36.0":{
               "pass":3
            },
            "5.37.9":{
               "fail":1,
               "pass":4
            }
         }
      },
      "Net-OnlineCode":{
         "0.04":{
            "5.36.0":{
               "pass":11
            },
            "5.37.9":{
               "fail":2,
               "pass":2
            }
         }
      },
      "Net-OpenSoundControl":{
         "0.05":{
            "5.36.0":{
               "pass":2
            },
            "5.37.9":{
               "fail":1,
               "pass":3
            }
         }
      },
      "Net-Ping-External":{
         "0.15":{
            "5.36.0":{
               "pass":14
            },
            "5.37.9":{
               "fail":4,
               "pass":25
            }
         }
      },
      "Net-Ping-Network":{
         "1.62":{
            "5.36.0":{
               "pass":1
            },
            "5.37.9":{
               "fail":2,
               "pass":2
            }
         }
      },
      "Net-Route":{
         "v0.02":{
            "5.36.0":{
               "fail":2
            },
            "5.37.9":{
               "fail":2,
               "pass":2
            }
         }
      },
      "Net-TCPwrappers":{
         "1.11":{
            "5.36.0":{
               "fail":1
            },
            "5.37.9":{
               "fail":3,
               "pass":1
            }
         }
      },
      "Net-XMPP":{
         "1.05":{
            "5.36.0":{
               "fail":7,
               "pass":15
            },
            "5.37.9":{
               "fail":5
            }
         }
      },
      "Net-Yadis":{
         "1.0":{
            "5.36.0":{
               "fail":6,
               "pass":12
            },
            "5.37.9":{
               "fail":4
            }
         }
      },
      "NetHack-FOV":{
         "0.01":{
            "5.36.0":{
               "pass":4
            },
            "5.37.9":{
               "fail":1,
               "pass":3
            }
         }
      },
      "Number-Format":{
         "1.75":{
            "5.36.0":{
               "fail":2,
               "pass":91
            },
            "5.37.9":{
               "fail":38
            }
         }
      },
      "OSDial":{
         "3.0.2.124":{
            "5.36.0":{
               "pass":2
            },
            "5.37.9":{
               "fail":1,
               "pass":3
            }
         }
      },
      "Object-Pad":{
         "0.78":{
            "5.36.0":{
               "pass":55
            },
            "5.37.9":{
               "fail":2,
               "pass":38
            }
         }
      },
      "Object-Remote":{
         "0.004001":{
            "5.36.0":{
               "pass":15
            },
            "5.37.9":{
               "fail":1,
               "pass":3
            }
         }
      },
      "OpenAI-API":{
         "0.11":{
            "5.36.0":{
               "fail":6,
               "pass":12
            },
            "5.37.9":{
               "fail":1
            }
         }
      },
      "OpenAPI-Modern":{
         "0.040":{
            "5.36.0":{
               "pass":16
            },
            "5.37.9":{
               "fail":1,
               "pass":9
            }
         }
      },
      "Oracle-DDL":{
         "0.10":{
            "5.36.0":{
               "fail":4
            },
            "5.37.9":{
               "fail":2,
               "pass":2
            }
         }
      },
      "Oracle-DML-Common":{
         "0.21":{
            "5.36.0":{
               "fail":11
            },
            "5.37.9":{
               "fail":2,
               "pass":2
            }
         }
      },
      "Oracle-Schema":{
         "0.02":{
            "5.36.0":{
               "fail":3
            },
            "5.37.9":{
               "fail":3,
               "pass":1
            }
         }
      },
      "Overload-FileCheck":{
         "0.013":{
            "5.36.0":{
               "pass":39
            },
            "5.37.9":{
               "fail":1,
               "pass":4
            }
         }
      },
      "PDL-Drawing-Prima":{
         "0.17":{
            "5.36.0":{
               "fail":1,
               "pass":4
            },
            "5.37.9":{
               "fail":2
            }
         }
      },
      "PFIX":{
         "0.03":{
            "5.36.0":{
               "fail":5,
               "pass":1
            },
            "5.37.9":{
               "fail":4
            }
         }
      },
      "POE-Component-Client-BigBrother":{
         "1.00":{
            "5.36.0":{
               "fail":10,
               "pass":3
            },
            "5.37.9":{
               "fail":3
            }
         }
      },
      "POE-Component-Client-MSN":{
         "0.03":{
            "5.36.0":{
               "pass":2
            },
            "5.37.9":{
               "fail":1,
               "pass":3
            }
         }
      },
      "POE-Component-Client-UserAgent":{
         "0.08":{
            "5.36.0":{
               "fail":8,
               "pass":5
            },
            "5.37.9":{
               "fail":5
            }
         }
      },
      "POE-Component-Generic":{
         "0.1403":{
            "5.36.0":{
               "fail":22,
               "pass":3
            },
            "5.37.9":{
               "fail":5
            }
         }
      },
      "POE-Component-MXML":{
         "0.03":{
            "5.36.0":{
               "pass":2
            },
            "5.37.9":{
               "fail":1,
               "pass":3
            }
         }
      },
      "POE-Component-Server-SimpleXMLRPC":{
         "0.02":{
            "5.36.0":{
               "fail":2
            },
            "5.37.9":{
               "fail":1,
               "pass":1
            }
         }
      },
      "POE-Future":{
         "0.04":{
            "5.36.0":{
               "pass":3
            },
            "5.37.9":{
               "fail":1,
               "pass":2
            }
         }
      },
      "PPR":{
         "0.001006":{
            "5.36.0":{
               "pass":48
            },
            "5.37.9":{
               "fail":4,
               "pass":26
            }
         }
      },
      "Palm-DiabetesPilot":{
         "1.08":{
            "5.36.0":{
               "pass":3
            },
            "5.37.9":{
               "fail":1,
               "pass":5
            }
         }
      },
      "Parse-Debian-PackageDesc":{
         "0.15":{
            "5.36.0":{
               "fail":21,
               "pass":2
            },
            "5.37.9":{
               "fail":4
            }
         }
      },
      "Parse-Vipar":{
         "0.01":{
            "5.36.0":{
               "fail":1
            },
            "5.37.9":{
               "fail":3,
               "pass":1
            }
         }
      },
      "Perinci-Sub-Gen-AccessTable-DBI":{
         "0.18":{
            "5.36.0":{
               "pass":1
            },
            "5.37.9":{
               "fail":2
            }
         }
      },
      "Perl-Builtins":{
         "0.04":{
            "5.36.0":{
               "pass":3
            },
            "5.37.9":{
               "fail":5
            }
         }
      },
      "PerlPowerTools":{
         "1.028":{
            "5.36.0":{
               "pass":23
            },
            "5.37.9":{
               "fail":14,
               "pass":15
            }
         }
      },
      "Pipeline":{
         "3.12":{
            "5.36.0":{
               "fail":11,
               "pass":1
            },
            "5.37.9":{
               "fail":4
            }
         }
      },
      "Plack-Middleware-Profiler-NYTProf":{
         "0.17":{
            "5.36.0":{
               "fail":20,
               "pass":1
            },
            "5.37.9":{
               "fail":4
            }
         }
      },
      "Plack-Server-AnyEvent":{
         "0.04":{
            "5.36.0":{
               "fail":18,
               "pass":1
            },
            "5.37.9":{
               "fail":5
            }
         }
      },
      "Plucene":{
         "1.25":{
            "5.36.0":{
               "fail":6,
               "pass":5
            },
            "5.37.9":{
               "fail":5
            }
         }
      },
      "Plucene-Plugin-Analyzer-SnowballAnalyzer":{
         "1.1":{
            "5.36.0":{
               "fail":5,
               "pass":5
            },
            "5.37.9":{
               "fail":5
            }
         }
      },
      "Pod-Trac":{
         "0.0.1":{
            "5.36.0":{
               "fail":1,
               "pass":1
            },
            "5.37.9":{
               "fail":4
            }
         }
      },
      "Poet":{
         "0.16":{
            "5.36.0":{
               "pass":10
            },
            "5.37.9":{
               "fail":3,
               "pass":1
            }
         }
      },
      "Poloniex-API":{
         "0.04":{
            "5.36.0":{
               "fail":10,
               "pass":1
            },
            "5.37.9":{
               "fail":4
            }
         }
      },
      "PostScript-PPD":{
         "0.0400":{
            "5.36.0":{
               "fail":1,
               "pass":11
            },
            "5.37.9":{
               "fail":1
            }
         },
         "0.0401":{
            "5.36.0":{
               "fail":1,
               "pass":11
            },
            "5.37.9":{
               "fail":1
            }
         }
      },
      "Proc-Launcher":{
         "0.0.37":{
            "5.36.0":{
               "fail":1,
               "pass":21
            },
            "5.37.9":{
               "fail":5
            }
         }
      },
      "Promise-AsyncAwait":{
         "0.01":{
            "5.36.0":{
               "fail":8,
               "pass":2
            },
            "5.37.9":{
               "fail":2
            }
         }
      },
      "Promise-XS":{
         "0.18":{
            "5.36.0":{
               "pass":31
            },
            "5.37.9":{
               "fail":3,
               "pass":3
            }
         }
      },
      "Protocol-Gearman":{
         "0.04":{
            "5.36.0":{
               "pass":2
            },
            "5.37.9":{
               "fail":1,
               "pass":4
            }
         }
      },
      "Protocol-HTTP2":{
         "1.10":{
            "5.36.0":{
               "fail":14,
               "pass":38
            },
            "5.37.9":{
               "fail":6
            }
         }
      },
      "Purple":{
         "1.4":{
            "5.36.0":{
               "pass":5
            },
            "5.37.9":{
               "fail":1,
               "pass":3
            }
         }
      },
      "R-YapRI":{
         "0.09":{
            "5.36.0":{
               "fail":8,
               "pass":9
            },
            "5.37.9":{
               "fail":6
            }
         }
      },
      "RDF-Notation3":{
         "0.91":{
            "5.36.0":{
               "fail":18,
               "pass":5
            },
            "5.37.9":{
               "fail":4
            }
         }
      },
      "REST-Client":{
         "281":{
            "5.36.0":{
               "pass":77
            },
            "5.37.9":{
               "fail":1,
               "pass":35
            }
         }
      },
      "Redis-Cluster-Fast":{
         "0.083":{
            "5.36.0":{
               "pass":7
            },
            "5.37.9":{
               "fail":1,
               "pass":3
            }
         }
      },
      "Redis-Dump":{
         "0.016":{
            "5.36.0":{
               "fail":2,
               "pass":1
            },
            "5.37.9":{
               "fail":4
            }
         }
      },
      "Redis-JobQueue":{
         "1.19":{
            "5.36.0":{
               "pass":6
            },
            "5.37.9":{
               "fail":1,
               "pass":4
            }
         }
      },
      "Regexp-Common-debian":{
         "v0.2.14":{
            "5.36.0":{
               "pass":15
            },
            "5.37.9":{
               "fail":1,
               "pass":5
            }
         }
      },
      "Repository-Simple":{
         "0.06":{
            "5.36.0":{
               "pass":1
            },
            "5.37.9":{
               "fail":1,
               "pass":3
            }
         }
      },
      "Rex-Template-Mojo":{
         "1.0":{
            "5.36.0":{
               "fail":6,
               "pass":5
            },
            "5.37.9":{
               "fail":4
            }
         }
      },
      "Rose-DBx-Object-Builder":{
         "0.09":{
            "5.36.0":{
               "fail":14
            },
            "5.37.9":{
               "fail":3,
               "pass":1
            }
         }
      },
      "SMS-API-CMTelecom":{
         "0.05":{
            "5.36.0":{
               "fail":7,
               "pass":3
            },
            "5.37.9":{
               "fail":4
            }
         }
      },
      "SPVM-FindBin":{
         "0.02":{
            "5.36.0":{
               "fail":1,
               "pass":3
            },
            "5.37.9":{
               "fail":1
            }
         }
      },
      "SPVM-IO":{
         "0.15":{
            "5.36.0":{
               "fail":3,
               "pass":7
            },
            "5.37.9":{
               "fail":1
            }
         }
      },
      "SQL-Validator":{
         "0.02":{
            "5.36.0":{
               "fail":2,
               "pass":3
            },
            "5.37.9":{
               "fail":4
            }
         }
      },
      "SQLite-Abstract":{
         "0.14":{
            "5.36.0":{
               "pass":2
            },
            "5.37.9":{
               "fail":2,
               "pass":2
            }
         }
      },
      "SVG-Convert-Driver-XAML":{
         "0.02":{
            "5.36.0":{
               "pass":2
            },
            "5.37.9":{
               "fail":5
            }
         }
      },
      "Scalar-Accessors-LikeHash":{
         "0.002":{
            "5.36.0":{
               "fail":4
            },
            "5.37.9":{
               "fail":4,
               "pass":1
            }
         }
      },
      "Schedule-Cron":{
         "1.04":{
            "5.36.0":{
               "fail":17,
               "pass":9
            },
            "5.37.9":{
               "fail":2
            }
         }
      },
      "Scope-Session":{
         "0.02":{
            "5.36.0":{
               "fail":1,
               "pass":16
            },
            "5.37.9":{
               "fail":4
            }
         }
      },
      "SeeAlso-Server":{
         "0.71":{
            "5.36.0":{
               "fail":5,
               "pass":1
            },
            "5.37.9":{
               "fail":3
            }
         }
      },
      "Sepia":{
         "0.992":{
            "5.36.0":{
               "fail":18,
               "pass":1
            },
            "5.37.9":{
               "fail":4
            }
         }
      },
      "Sereal-Decoder":{
         "5.001_002":{
            "5.36.0":{
               "fail":1,
               "pass":8
            },
            "5.37.9":{
               "fail":1
            }
         },
         "5.001_003":{
            "5.36.0":{
               "fail":1,
               "pass":4
            },
            "5.37.9":{
               "fail":1
            }
         }
      },
      "Serge":{
         "1.4":{
            "5.36.0":{
               "fail":7,
               "pass":6
            },
            "5.37.9":{
               "fail":6
            }
         }
      },
      "Serge-Sync-Plugin-TranslationService-Smartcat":{
         "0.0.6":{
            "5.36.0":{
               "fail":5,
               "pass":1
            },
            "5.37.9":{
               "fail":4
            }
         }
      },
      "SimpleCDB":{
         "1.0":{
            "5.36.0":{
               "fail":1,
               "pass":1
            },
            "5.37.9":{
               "fail":4
            }
         }
      },
      "Slay-Makefile":{
         "0.13":{
            "5.36.0":{
               "pass":22
            },
            "5.37.9":{
               "fail":10
            }
         }
      },
      "Sort-Naturally-XS":{
         "0.7.9":{
            "5.36.0":{
               "pass":6
            },
            "5.37.9":{
               "fail":1,
               "pass":3
            }
         }
      },
      "Splunk-HEC":{
         "1.02":{
            "5.36.0":{
               "pass":4
            },
            "5.37.9":{
               "fail":1,
               "pass":4
            }
         }
      },
      "Spreadsheet-ParseExcel":{
         "0.65":{
            "5.36.0":{
               "pass":79
            },
            "5.37.9":{
               "fail":1,
               "pass":39
            }
         }
      },
      "Spreadsheet-ReadGnumeric":{
         "0.1":{
            "5.36.0":{
               "fail":9,
               "pass":12
            },
            "5.37.9":{
               "fail":1
            }
         }
      },
      "Stor":{
         "1.5.2":{
            "5.36.0":{
               "pass":1
            },
            "5.37.9":{
               "fail":1,
               "pass":3
            }
         }
      },
      "Struct-Dumb":{
         "0.13":{
            "5.36.0":{
               "pass":74
            },
            "5.37.9":{
               "fail":1,
               "pass":19
            }
         }
      },
      "Syntax-Keyword-Dynamically":{
         "0.11":{
            "5.36.0":{
               "pass":43
            },
            "5.37.9":{
               "fail":3,
               "pass":34
            }
         }
      },
      "Sys-HostAddr":{
         "0.993":{
            "5.36.0":{
               "fail":15
            },
            "5.37.9":{
               "fail":2,
               "pass":3
            }
         }
      },
      "Sys-Mmap":{
         "0.20":{
            "5.36.0":{
               "pass":17
            },
            "5.37.9":{
               "fail":4,
               "pass":24
            }
         }
      },
      "TAP-Formatter-BambooExtended":{
         "1.01":{
            "5.36.0":{
               "fail":5,
               "pass":2
            },
            "5.37.9":{
               "fail":6
            }
         }
      },
      "Tatsumaki":{
         "0.1013":{
            "5.36.0":{
               "fail":24,
               "pass":1
            },
            "5.37.9":{
               "fail":5
            }
         }
      },
      "Template-Plugin-SafeInclude":{
         "0.02":{
            "5.36.0":{
               "fail":3,
               "pass":2
            },
            "5.37.9":{
               "fail":5
            }
         }
      },
      "Template-Plugin-Text-Widont":{
         "0.01":{
            "5.36.0":{},
            "5.37.9":{
               "fail":3,
               "pass":1
            }
         }
      },
      "Template-Plugin-WebService":{
         "0.16":{
            "5.36.0":{
               "fail":5
            },
            "5.37.9":{
               "fail":2,
               "pass":3
            }
         }
      },
      "Template-Provider-DBIC":{
         "0.02":{
            "5.36.0":{
               "fail":4
            },
            "5.37.9":{
               "fail":3,
               "pass":1
            }
         }
      },
      "Template-Provider-PrefixDBIC":{
         "0.01":{
            "5.36.0":{
               "fail":4
            },
            "5.37.9":{
               "fail":4,
               "pass":1
            }
         }
      },
      "Term-Caca":{
         "3.1.0":{
            "5.36.0":{
               "pass":4
            },
            "5.37.9":{
               "fail":3,
               "pass":1
            }
         }
      },
      "Term-Clear":{
         "0.01":{
            "5.36.0":{
               "fail":18,
               "pass":11
            },
            "5.37.9":{
               "fail":4
            }
         }
      },
      "Term-ReadLine-Gnu":{
         "1.45":{
            "5.36.0":{
               "pass":31
            },
            "5.37.9":{
               "fail":4,
               "pass":31
            }
         }
      },
      "Termbox":{
         "0.12":{
            "5.36.0":{
               "fail":19,
               "pass":2
            },
            "5.37.9":{
               "fail":4
            }
         }
      },
      "Test-Approximate":{
         "0.009":{
            "5.36.0":{
               "fail":2
            },
            "5.37.9":{
               "fail":2,
               "pass":2
            }
         }
      },
      "Test-Benchmark":{
         "0.004":{
            "5.36.0":{
               "fail":8,
               "pass":1
            },
            "5.37.9":{
               "fail":5
            }
         }
      },
      "Test-CGI-Multipart":{
         "v0.0.3":{
            "5.36.0":{
               "fail":20,
               "pass":1
            },
            "5.37.9":{
               "fail":3
            }
         }
      },
      "Test-Fixture-DBI":{
         "0.09":{
            "5.36.0":{
               "pass":11
            },
            "5.37.9":{
               "fail":2,
               "pass":2
            }
         }
      },
      "Test-HTTP-AnyEvent-Server":{
         "0.013":{
            "5.36.0":{
               "fail":10,
               "pass":2
            },
            "5.37.9":{
               "fail":5
            }
         }
      },
      "Test-Mini":{
         "v1.1.3":{
            "5.36.0":{
               "fail":16,
               "pass":3
            },
            "5.37.9":{
               "fail":5
            }
         }
      },
      "Test-Reporter-Transport-Net-SMTP-SSL":{
         "0.1.2":{
            "5.36.0":{
               "fail":2
            },
            "5.37.9":{
               "fail":2,
               "pass":2
            }
         }
      },
      "Test-Strict":{
         "0.52":{
            "5.36.0":{
               "pass":64
            },
            "5.37.9":{
               "fail":36
            }
         }
      },
      "Test-Vars":{
         "0.015":{
            "5.36.0":{
               "pass":65
            },
            "5.37.9":{
               "fail":32,
               "pass":2
            }
         }
      },
      "Test-XML-Simple":{
         "1.05":{
            "5.36.0":{
               "fail":10,
               "pass":2
            },
            "5.37.9":{
               "fail":5
            }
         }
      },
      "Text-Bidi":{
         "2.18":{
            "5.36.0":{
               "fail":9,
               "pass":2
            },
            "5.37.9":{
               "fail":5
            }
         }
      },
      "Text-Echelon":{
         "0.02":{
            "5.36.0":{
               "pass":3
            },
            "5.37.9":{
               "fail":2,
               "pass":3
            }
         }
      },
      "Text-MacroScript":{
         "2.11":{
            "5.36.0":{
               "pass":3
            },
            "5.37.9":{
               "fail":6
            }
         }
      },
      "Text-Match-FastAlternatives":{
         "1.05":{
            "5.36.0":{
               "fail":3
            },
            "5.37.9":{
               "fail":3,
               "pass":2
            }
         }
      },
      "Text-MicroMason":{
         "2.23":{
            "5.36.0":{
               "pass":15
            },
            "5.37.9":{
               "fail":6
            }
         }
      },
      "Text-SimpleVaddrbook":{
         "0.01":{
            "5.36.0":{
               "fail":2
            },
            "5.37.9":{
               "fail":3,
               "pass":3
            }
         }
      },
      "Text-Template-Compact":{
         "0.1.12":{
            "5.36.0":{
               "pass":3
            },
            "5.37.9":{
               "fail":6
            }
         }
      },
      "Text-Trac2GFM":{
         "0.001":{
            "5.36.0":{
               "pass":4
            },
            "5.37.9":{
               "fail":4
            }
         }
      },
      "Text-XmlMatch":{
         "1.0006":{
            "5.36.0":{
               "fail":2,
               "pass":3
            },
            "5.37.9":{
               "fail":4
            }
         }
      },
      "Text-Xslate-Bridge-TypeDeclaration":{
         "0.13":{
            "5.36.0":{
               "fail":5,
               "pass":3
            },
            "5.37.9":{
               "fail":4
            }
         }
      },
      "Thread-Csp":{
         "0.009":{
            "5.36.0":{
               "pass":6
            },
            "5.37.9":{
               "fail":2,
               "pass":13
            }
         }
      },
      "Tie-Comma":{
         "0.04":{
            "5.36.0":{
               "pass":6
            },
            "5.37.9":{
               "fail":2,
               "pass":3
            }
         }
      },
      "Tie-NumericRange":{
         "0.01":{
            "5.36.0":{
               "fail":2
            },
            "5.37.9":{
               "fail":1,
               "pass":3
            }
         }
      },
      "Tie-ShareLite":{
         "0.03":{
            "5.36.0":{
               "pass":2
            },
            "5.37.9":{
               "fail":1,
               "pass":3
            }
         }
      },
      "Time-Zone-Olson":{
         "0.45":{
            "5.36.0":{
               "pass":11
            },
            "5.37.9":{
               "fail":4,
               "pass":19
            }
         }
      },
      "Timeout-Queue":{
         "1.02":{
            "5.36.0":{
               "fail":1,
               "pass":2
            },
            "5.37.9":{
               "fail":4
            }
         }
      },
      "Tk-BarberPole":{
         "0.01":{
            "5.36.0":{
               "pass":2
            },
            "5.37.9":{
               "fail":2,
               "pass":3
            }
         }
      },
      "Tk-CanvasDirTree":{
         "0.04":{
            "5.36.0":{
               "pass":2
            },
            "5.37.9":{
               "fail":1,
               "pass":3
            }
         }
      },
      "Tk-Contrib":{
         "0.07":{
            "5.36.0":{
               "pass":2
            },
            "5.37.9":{
               "fail":1,
               "pass":3
            }
         }
      },
      "Tk-DirSelect":{
         "1.12":{
            "5.36.0":{
               "fail":26,
               "pass":11
            },
            "5.37.9":{
               "fail":5
            }
         }
      },
      "Tk-EntryDialog":{
         "0.10":{
            "5.36.0":{
               "pass":3
            },
            "5.37.9":{
               "fail":1,
               "pass":3
            }
         }
      },
      "Tk-MDI":{
         "0.2":{
            "5.36.0":{
               "pass":3
            },
            "5.37.9":{
               "fail":1,
               "pass":3
            }
         }
      },
      "Tk-MouseGesture":{
         "0.03":{
            "5.36.0":{
               "pass":2
            },
            "5.37.9":{
               "fail":1,
               "pass":4
            }
         }
      },
      "Tk-Task":{
         "1.1":{
            "5.36.0":{},
            "5.37.9":{
               "fail":1,
               "pass":4
            }
         }
      },
      "Tk-Zinc":{
         "3.306":{
            "5.36.0":{
               "fail":16,
               "pass":9
            },
            "5.37.9":{
               "fail":4
            }
         }
      },
      "Tk-autobind":{
         "1.2":{
            "5.36.0":{
               "pass":3
            },
            "5.37.9":{
               "fail":1,
               "pass":3
            }
         }
      },
      "TkGenerator":{
         "00.1a":{
            "5.36.0":{
               "pass":2
            },
            "5.37.9":{
               "fail":1,
               "pass":3
            }
         }
      },
      "Tool-Bench":{
         "0.003":{
            "5.36.0":{
               "pass":9
            },
            "5.37.9":{
               "fail":2,
               "pass":4
            }
         }
      },
      "UML-Class-Simple":{
         "0.22":{
            "5.36.0":{
               "fail":8,
               "pass":6
            },
            "5.37.9":{
               "fail":4
            }
         }
      },
      "UML-State":{
         "0.02":{
            "5.36.0":{
               "fail":3
            },
            "5.37.9":{
               "fail":3,
               "pass":1
            }
         }
      },
      "UR":{
         "0.47":{
            "5.36.0":{
               "pass":16
            },
            "5.37.9":{
               "fail":6
            }
         }
      },
      "URI-ParseSearchString":{
         "3.51":{
            "5.36.0":{
               "fail":7,
               "pass":5
            },
            "5.37.9":{
               "fail":4
            }
         }
      },
      "URI-Title":{
         "1.903":{
            "5.36.0":{
               "fail":13,
               "pass":17
            },
            "5.37.9":{
               "fail":1
            }
         }
      },
      "Unix-Mgt":{
         "0.14":{
            "5.36.0":{
               "fail":1,
               "pass":3
            },
            "5.37.9":{
               "fail":4
            }
         }
      },
      "WWW-BetfairNG":{
         "0.15":{
            "5.36.0":{
               "pass":4
            },
            "5.37.9":{
               "fail":1,
               "pass":3
            }
         }
      },
      "WWW-DoctypeGrabber":{
         "0.007":{
            "5.36.0":{
               "fail":23,
               "pass":1
            },
            "5.37.9":{
               "fail":5
            }
         }
      },
      "WWW-Hatena-WanWanWorld":{
         "0.02":{
            "5.36.0":{
               "fail":7,
               "pass":1
            },
            "5.37.9":{
               "fail":4
            }
         }
      },
      "WWW-Postmark":{
         "1.000001":{
            "5.36.0":{
               "pass":15
            },
            "5.37.9":{
               "fail":5
            }
         }
      },
      "WWW-RSSFeed":{
         "0.01":{
            "5.36.0":{},
            "5.37.9":{
               "fail":3,
               "pass":1
            }
         }
      },
      "WWW-Scraper-ISBN-TWBooks_Driver":{
         "0.02":{
            "5.36.0":{
               "fail":5,
               "pass":2
            },
            "5.37.9":{
               "fail":3
            }
         }
      },
      "WWW-Scraper-ISBN-TWSrbook_Driver":{
         "0.01":{
            "5.36.0":{
               "pass":2
            },
            "5.37.9":{
               "fail":3
            }
         }
      },
      "WWW-Search-Ebay":{
         "3.056":{
            "5.36.0":{
               "fail":13,
               "pass":3
            },
            "5.37.9":{
               "fail":4
            }
         }
      },
      "WWW-Wikipedia":{
         "2.05":{
            "5.36.0":{
               "pass":9
            },
            "5.37.9":{
               "fail":1,
               "pass":5
            }
         }
      },
      "Waft-JSON":{
         "0.03":{
            "5.36.0":{
               "fail":5
            },
            "5.37.9":{
               "fail":3,
               "pass":1
            }
         }
      },
      "Weather-Meteo":{
         "0.01":{
            "5.36.0":{
               "fail":3,
               "pass":4
            },
            "5.37.9":{
               "fail":1
            }
         }
      },
      "Web-PageMeta":{
         "0.07":{
            "5.36.0":{
               "pass":2
            },
            "5.37.9":{
               "fail":1,
               "pass":1
            }
         }
      },
      "Web-Simple":{
         "0.033":{
            "5.36.0":{
               "pass":21
            },
            "5.37.9":{
               "fail":1,
               "pass":20
            }
         }
      },
      "WebService-Async-UserAgent":{
         "0.006":{
            "5.36.0":{
               "pass":6
            },
            "5.37.9":{
               "fail":1,
               "pass":1
            }
         }
      },
      "WebService-ClinicalTrialsdotGov":{
         "0.04":{
            "5.36.0":{
               "pass":7
            },
            "5.37.9":{
               "fail":1,
               "pass":3
            }
         }
      },
      "WebService-FOAAS":{
         "0.002":{
            "5.36.0":{
               "fail":8,
               "pass":4
            },
            "5.37.9":{
               "fail":4
            }
         }
      },
      "WebService-Google-Contact":{
         "0.1":{
            "5.36.0":{
               "fail":3,
               "pass":1
            },
            "5.37.9":{
               "fail":4
            }
         }
      },
      "WebService-Google-Language":{
         "0.14":{
            "5.36.0":{
               "fail":14,
               "pass":1
            },
            "5.37.9":{
               "fail":4
            }
         }
      },
      "WebService-Lucene":{
         "0.10":{
            "5.36.0":{
               "fail":9,
               "pass":1
            },
            "5.37.9":{
               "fail":5
            }
         }
      },
      "WebService-Simple-Google-Chart":{
         "0.05":{
            "5.36.0":{
               "fail":4,
               "pass":3
            },
            "5.37.9":{
               "fail":4
            }
         }
      },
      "WebService-Uptrack":{
         "v0.0.2":{
            "5.36.0":{
               "fail":3,
               "pass":1
            },
            "5.37.9":{
               "fail":4
            }
         }
      },
      "Webservice-InterMine":{
         "1.0405":{
            "5.36.0":{
               "pass":4
            },
            "5.37.9":{
               "fail":1
            }
         }
      },
      "Wishlist":{
         "0.02":{
            "5.36.0":{
               "fail":2,
               "pass":6
            },
            "5.37.9":{
               "fail":4
            }
         }
      },
      "XML-APML":{
         "0.04":{
            "5.36.0":{
               "fail":2,
               "pass":1
            },
            "5.37.9":{
               "fail":4
            }
         }
      },
      "XML-Clean":{
         "1.06":{
            "5.36.0":{
               "pass":3
            },
            "5.37.9":{
               "fail":3,
               "pass":1
            }
         }
      },
      "XML-SAX-Builder":{
         "0.02":{
            "5.36.0":{
               "fail":1
            },
            "5.37.9":{
               "fail":4,
               "pass":1
            }
         }
      },
      "XML-SAXDriver-CSV":{
         "0.07":{
            "5.36.0":{
               "pass":1
            },
            "5.37.9":{
               "fail":1,
               "pass":3
            }
         }
      },
      "XML-Schematron":{
         "1.10":{
            "5.36.0":{
               "pass":56
            },
            "5.37.9":{
               "fail":1,
               "pass":4
            }
         }
      },
      "XML-XPathScript":{
         "2.00":{
            "5.36.0":{
               "pass":14
            },
            "5.37.9":{
               "fail":4
            }
         }
      },
      "XMLNews-HTMLTemplate":{
         "0.01":{
            "5.36.0":{},
            "5.37.9":{
               "fail":4,
               "pass":1
            }
         }
      },
      "cPanel-APIClient":{
         "0.10":{
            "5.36.0":{
               "pass":53
            },
            "5.37.9":{
               "fail":1,
               "pass":3
            }
         }
      },
      "filename":{
         "v0.20.060":{
            "5.36.0":{
               "pass":2
            },
            "5.37.9":{
               "fail":5
            }
         }
      },
      "fork-hook":{
         "0.02":{
            "5.36.0":{
               "fail":1
            },
            "5.37.9":{
               "fail":2,
               "pass":2
            }
         }
      },
      "makepp":{
         "2.0.99.2":{
            "5.36.0":{
               "fail":3
            },
            "5.37.9":{
               "fail":2,
               "pass":2
            }
         }
      },
      "mojo-debugbar":{
         "0.0.5":{
            "5.36.0":{
               "fail":17,
               "pass":3
            },
            "5.37.9":{
               "fail":4
            }
         }
      },
      "oo_sub":{
         "v1.0.9":{
            "5.36.0":{
               "fail":7,
               "pass":16
            },
            "5.37.9":{
               "fail":5
            }
         }
      },
      "openStatisticalServices":{
         "0.022":{
            "5.36.0":{
               "pass":2
            },
            "5.37.9":{
               "fail":2,
               "pass":3
            }
         }
      },
      "parent-versioned":{
         "0.002":{
            "5.36.0":{
               "pass":2
            },
            "5.37.9":{
               "fail":4
            }
         }
      },
      "pod2book":{
         "0.0.1":{
            "5.36.0":{
               "fail":2
            },
            "5.37.9":{
               "fail":4,
               "pass":1
            }
         }
      },
      "tkShortcuts":{
         "1.00a":{
            "5.36.0":{
               "pass":2
            },
            "5.37.9":{
               "fail":1,
               "pass":3
            }
         }
      },
      "wikitext-perl":{
         "1.01":{
            "5.36.0":{
               "fail":4
            },
            "5.37.9":{
               "fail":2,
               "pass":2
            }
         }
      }
   }
}
